simple circuit/and gate simulation/structural/myAnd.v
//This module simulates the behavour of AND gate 
//Created by Soumik Guha Roy
module myAnd(a,b,c);
	input a,b;
	output c;

	reg c;

	always @(a or b)
	begin
	//Whenever a or b changes this block executes
		if ( ((a==1'b1) && (b==1'b1) ))
		begin
			c =1'b1;
			$monitor("I am at if part");
			
		end
		else
			c=1'b0;
			$monitor("I am at else part");			

	end
endmodule
//End of the module

simple circuit/and gate simulation/structural/tb.v
//This is the test bench for the and gate 
//Created by Soumik Guha Roy
module tb;
	reg[1:0] myData;

	myAnd a(myData[1],myData[0],c);
	initial begin
		myData=2'b00;
		$dumpfile("wave.vcd");
		$dumpvars(0,tb);
		#500 $finish;
	end
	always
		#1 myData<=myData+1;
	initial begin
		$monitor("\nmyData[1]: %b\tmyData[0]: %b\tc=%b",myData[1],myData[0],c);
	end

endmodule

simple circuit/and gate simulation/structural/wave.vcd
$date
	Wed Jul 18 21:15:05 2018
$end
$version
	Icarus Verilog
$end
$timescale
	1s
$end
$scope module tb $end
$var wire 1 ! c $end
$var reg 2 " myData [1:0] $end
$scope module a $end
$var wire 1 # a $end
$var wire 1 $ b $end
$var reg 1 % c $end
$upscope $end
$upscope $end
$enddefinitions $end
#0
$dumpvars
0%
0$
0#
b0 "
0!
$end
#1
1$
b1 "
#2
1#
0$
b10 "
#3
1%
1!
1$
b11 "
#4
0%
0!
0#
0$
b0 "
#5
1$
b1 "
#6
1#
0$
b10 "
#7
1%
1!
1$
b11 "
#8
0%
0!
0#
0$
b0 "
#9
1$
b1 "
#10
1#
0$
b10 "
#11
1%
1!
1$
b11 "
#12
0%
0!
0#
0$
b0 "
#13
1$
b1 "
#14
1#
0$
b10 "
#15
1%
1!
1$
b11 "
#16
0%
0!
0#
0$
b0 "
#17
1$
b1 "
#18
1#
0$
b10 "
#19
1%
1!
1$
b11 "
#20
0%
0!
0#
0$
b0 "
#21
1$
b1 "
#22
1#
0$
b10 "
#23
1%
1!
1$
b11 "
#24
0%
0!
0#
0$
b0 "
#25
1$
b1 "
#26
1#
0$
b10 "
#27
1%
1!
1$
b11 "
#28
0%
0!
0#
0$
b0 "
#29
1$
b1 "
#30
1#
0$
b10 "
#31
1%
1!
1$
b11 "
#32
0%
0!
0#
0$
b0 "
#33
1$
b1 "
#34
1#
0$
b10 "
#35
1%
1!
1$
b11 "
#36
0%
0!
0#
0$
b0 "
#37
1$
b1 "
#38
1#
0$
b10 "
#39
1%
1!
1$
b11 "
#40
0%
0!
0#
0$
b0 "
#41
1$
b1 "
#42
1#
0$
b10 "
#43
1%
1!
1$
b11 "
#44
0%
0!
0#
0$
b0 "
#45
1$
b1 "
#46
1#
0$
b10 "
#47
1%
1!
1$
b11 "
#48
0%
0!
0#
0$
b0 "
#49
1$
b1 "
#50
1#
0$
b10 "
#51
1%
1!
1$
b11 "
#52
0%
0!
0#
0$
b0 "
#53
1$
b1 "
#54
1#
0$
b10 "
#55
1%
1!
1$
b11 "
#56
0%
0!
0#
0$
b0 "
#57
1$
b1 "
#58
1#
0$
b10 "
#59
1%
1!
1$
b11 "
#60
0%
0!
0#
0$
b0 "
#61
1$
b1 "
#62
1#
0$
b10 "
#63
1%
1!
1$
b11 "
#64
0%
0!
0#
0$
b0 "
#65
1$
b1 "
#66
1#
0$
b10 "
#67
1%
1!
1$
b11 "
#68
0%
0!
0#
0$
b0 "
#69
1$
b1 "
#70
1#
0$
b10 "
#71
1%
1!
1$
b11 "
#72
0%
0!
0#
0$
b0 "
#73
1$
b1 "
#74
1#
0$
b10 "
#75
1%
1!
1$
b11 "
#76
0%
0!
0#
0$
b0 "
#77
1$
b1 "
#78
1#
0$
b10 "
#79
1%
1!
1$
b11 "
#80
0%
0!
0#
0$
b0 "
#81
1$
b1 "
#82
1#
0$
b10 "
#83
1%
1!
1$
b11 "
#84
0%
0!
0#
0$
b0 "
#85
1$
b1 "
#86
1#
0$
b10 "
#87
1%
1!
1$
b11 "
#88
0%
0!
0#
0$
b0 "
#89
1$
b1 "
#90
1#
0$
b10 "
#91
1%
1!
1$
b11 "
#92
0%
0!
0#
0$
b0 "
#93
1$
b1 "
#94
1#
0$
b10 "
#95
1%
1!
1$
b11 "
#96
0%
0!
0#
0$
b0 "
#97
1$
b1 "
#98
1#
0$
b10 "
#99
1%
1!
1$
b11 "
#100
0%
0!
0#
0$
b0 "
#101
1$
b1 "
#102
1#
0$
b10 "
#103
1%
1!
1$
b11 "
#104
0%
0!
0#
0$
b0 "
#105
1$
b1 "
#106
1#
0$
b10 "
#107
1%
1!
1$
b11 "
#108
0%
0!
0#
0$
b0 "
#109
1$
b1 "
#110
1#
0$
b10 "
#111
1%
1!
1$
b11 "
#112
0%
0!
0#
0$
b0 "
#113
1$
b1 "
#114
1#
0$
b10 "
#115
1%
1!
1$
b11 "
#116
0%
0!
0#
0$
b0 "
#117
1$
b1 "
#118
1#
0$
b10 "
#119
1%
1!
1$
b11 "
#120
0%
0!
0#
0$
b0 "
#121
1$
b1 "
#122
1#
0$
b10 "
#123
1%
1!
1$
b11 "
#124
0%
0!
0#
0$
b0 "
#125
1$
b1 "
#126
1#
0$
b10 "
#127
1%
1!
1$
b11 "
#128
0%
0!
0#
0$
b0 "
#129
1$
b1 "
#130
1#
0$
b10 "
#131
1%
1!
1$
b11 "
#132
0%
0!
0#
0$
b0 "
#133
1$
b1 "
#134
1#
0$
b10 "
#135
1%
1!
1$
b11 "
#136
0%
0!
0#
0$
b0 "
#137
1$
b1 "
#138
1#
0$
b10 "
#139
1%
1!
1$
b11 "
#140
0%
0!
0#
0$
b0 "
#141
1$
b1 "
#142
1#
0$
b10 "
#143
1%
1!
1$
b11 "
#144
0%
0!
0#
0$
b0 "
#145
1$
b1 "
#146
1#
0$
b10 "
#147
1%
1!
1$
b11 "
#148
0%
0!
0#
0$
b0 "
#149
1$
b1 "
#150
1#
0$
b10 "
#151
1%
1!
1$
b11 "
#152
0%
0!
0#
0$
b0 "
#153
1$
b1 "
#154
1#
0$
b10 "
#155
1%
1!
1$
b11 "
#156
0%
0!
0#
0$
b0 "
#157
1$
b1 "
#158
1#
0$
b10 "
#159
1%
1!
1$
b11 "
#160
0%
0!
0#
0$
b0 "
#161
1$
b1 "
#162
1#
0$
b10 "
#163
1%
1!
1$
b11 "
#164
0%
0!
0#
0$
b0 "
#165
1$
b1 "
#166
1#
0$
b10 "
#167
1%
1!
1$
b11 "
#168
0%
0!
0#
0$
b0 "
#169
1$
b1 "
#170
1#
0$
b10 "
#171
1%
1!
1$
b11 "
#172
0%
0!
0#
0$
b0 "
#173
1$
b1 "
#174
1#
0$
b10 "
#175
1%
1!
1$
b11 "
#176
0%
0!
0#
0$
b0 "
#177
1$
b1 "
#178
1#
0$
b10 "
#179
1%
1!
1$
b11 "
#180
0%
0!
0#
0$
b0 "
#181
1$
b1 "
#182
1#
0$
b10 "
#183
1%
1!
1$
b11 "
#184
0%
0!
0#
0$
b0 "
#185
1$
b1 "
#186
1#
0$
b10 "
#187
1%
1!
1$
b11 "
#188
0%
0!
0#
0$
b0 "
#189
1$
b1 "
#190
1#
0$
b10 "
#191
1%
1!
1$
b11 "
#192
0%
0!
0#
0$
b0 "
#193
1$
b1 "
#194
1#
0$
b10 "
#195
1%
1!
1$
b11 "
#196
0%
0!
0#
0$
b0 "
#197
1$
b1 "
#198
1#
0$
b10 "
#199
1%
1!
1$
b11 "
#200
0%
0!
0#
0$
b0 "
#201
1$
b1 "
#202
1#
0$
b10 "
#203
1%
1!
1$
b11 "
#204
0%
0!
0#
0$
b0 "
#205
1$
b1 "
#206
1#
0$
b10 "
#207
1%
1!
1$
b11 "
#208
0%
0!
0#
0$
b0 "
#209
1$
b1 "
#210
1#
0$
b10 "
#211
1%
1!
1$
b11 "
#212
0%
0!
0#
0$
b0 "
#213
1$
b1 "
#214
1#
0$
b10 "
#215
1%
1!
1$
b11 "
#216
0%
0!
0#
0$
b0 "
#217
1$
b1 "
#218
1#
0$
b10 "
#219
1%
1!
1$
b11 "
#220
0%
0!
0#
0$
b0 "
#221
1$
b1 "
#222
1#
0$
b10 "
#223
1%
1!
1$
b11 "
#224
0%
0!
0#
0$
b0 "
#225
1$
b1 "
#226
1#
0$
b10 "
#227
1%
1!
1$
b11 "
#228
0%
0!
0#
0$
b0 "
#229
1$
b1 "
#230
1#
0$
b10 "
#231
1%
1!
1$
b11 "
#232
0%
0!
0#
0$
b0 "
#233
1$
b1 "
#234
1#
0$
b10 "
#235
1%
1!
1$
b11 "
#236
0%
0!
0#
0$
b0 "
#237
1$
b1 "
#238
1#
0$
b10 "
#239
1%
1!
1$
b11 "
#240
0%
0!
0#
0$
b0 "
#241
1$
b1 "
#242
1#
0$
b10 "
#243
1%
1!
1$
b11 "
#244
0%
0!
0#
0$
b0 "
#245
1$
b1 "
#246
1#
0$
b10 "
#247
1%
1!
1$
b11 "
#248
0%
0!
0#
0$
b0 "
#249
1$
b1 "
#250
1#
0$
b10 "
#251
1%
1!
1$
b11 "
#252
0%
0!
0#
0$
b0 "
#253
1$
b1 "
#254
1#
0$
b10 "
#255
1%
1!
1$
b11 "
#256
0%
0!
0#
0$
b0 "
#257
1$
b1 "
#258
1#
0$
b10 "
#259
1%
1!
1$
b11 "
#260
0%
0!
0#
0$
b0 "
#261
1$
b1 "
#262
1#
0$
b10 "
#263
1%
1!
1$
b11 "
#264
0%
0!
0#
0$
b0 "
#265
1$
b1 "
#266
1#
0$
b10 "
#267
1%
1!
1$
b11 "
#268
0%
0!
0#
0$
b0 "
#269
1$
b1 "
#270
1#
0$
b10 "
#271
1%
1!
1$
b11 "
#272
0%
0!
0#
0$
b0 "
#273
1$
b1 "
#274
1#
0$
b10 "
#275
1%
1!
1$
b11 "
#276
0%
0!
0#
0$
b0 "
#277
1$
b1 "
#278
1#
0$
b10 "
#279
1%
1!
1$
b11 "
#280
0%
0!
0#
0$
b0 "
#281
1$
b1 "
#282
1#
0$
b10 "
#283
1%
1!
1$
b11 "
#284
0%
0!
0#
0$
b0 "
#285
1$
b1 "
#286
1#
0$
b10 "
#287
1%
1!
1$
b11 "
#288
0%
0!
0#
0$
b0 "
#289
1$
b1 "
#290
1#
0$
b10 "
#291
1%
1!
1$
b11 "
#292
0%
0!
0#
0$
b0 "
#293
1$
b1 "
#294
1#
0$
b10 "
#295
1%
1!
1$
b11 "
#296
0%
0!
0#
0$
b0 "
#297
1$
b1 "
#298
1#
0$
b10 "
#299
1%
1!
1$
b11 "
#300
0%
0!
0#
0$
b0 "
#301
1$
b1 "
#302
1#
0$
b10 "
#303
1%
1!
1$
b11 "
#304
0%
0!
0#
0$
b0 "
#305
1$
b1 "
#306
1#
0$
b10 "
#307
1%
1!
1$
b11 "
#308
0%
0!
0#
0$
b0 "
#309
1$
b1 "
#310
1#
0$
b10 "
#311
1%
1!
1$
b11 "
#312
0%
0!
0#
0$
b0 "
#313
1$
b1 "
#314
1#
0$
b10 "
#315
1%
1!
1$
b11 "
#316
0%
0!
0#
0$
b0 "
#317
1$
b1 "
#318
1#
0$
b10 "
#319
1%
1!
1$
b11 "
#320
0%
0!
0#
0$
b0 "
#321
1$
b1 "
#322
1#
0$
b10 "
#323
1%
1!
1$
b11 "
#324
0%
0!
0#
0$
b0 "
#325
1$
b1 "
#326
1#
0$
b10 "
#327
1%
1!
1$
b11 "
#328
0%
0!
0#
0$
b0 "
#329
1$
b1 "
#330
1#
0$
b10 "
#331
1%
1!
1$
b11 "
#332
0%
0!
0#
0$
b0 "
#333
1$
b1 "
#334
1#
0$
b10 "
#335
1%
1!
1$
b11 "
#336
0%
0!
0#
0$
b0 "
#337
1$
b1 "
#338
1#
0$
b10 "
#339
1%
1!
1$
b11 "
#340
0%
0!
0#
0$
b0 "
#341
1$
b1 "
#342
1#
0$
b10 "
#343
1%
1!
1$
b11 "
#344
0%
0!
0#
0$
b0 "
#345
1$
b1 "
#346
1#
0$
b10 "
#347
1%
1!
1$
b11 "
#348
0%
0!
0#
0$
b0 "
#349
1$
b1 "
#350
1#
0$
b10 "
#351
1%
1!
1$
b11 "
#352
0%
0!
0#
0$
b0 "
#353
1$
b1 "
#354
1#
0$
b10 "
#355
1%
1!
1$
b11 "
#356
0%
0!
0#
0$
b0 "
#357
1$
b1 "
#358
1#
0$
b10 "
#359
1%
1!
1$
b11 "
#360
0%
0!
0#
0$
b0 "
#361
1$
b1 "
#362
1#
0$
b10 "
#363
1%
1!
1$
b11 "
#364
0%
0!
0#
0$
b0 "
#365
1$
b1 "
#366
1#
0$
b10 "
#367
1%
1!
1$
b11 "
#368
0%
0!
0#
0$
b0 "
#369
1$
b1 "
#370
1#
0$
b10 "
#371
1%
1!
1$
b11 "
#372
0%
0!
0#
0$
b0 "
#373
1$
b1 "
#374
1#
0$
b10 "
#375
1%
1!
1$
b11 "
#376
0%
0!
0#
0$
b0 "
#377
1$
b1 "
#378
1#
0$
b10 "
#379
1%
1!
1$
b11 "
#380
0%
0!
0#
0$
b0 "
#381
1$
b1 "
#382
1#
0$
b10 "
#383
1%
1!
1$
b11 "
#384
0%
0!
0#
0$
b0 "
#385
1$
b1 "
#386
1#
0$
b10 "
#387
1%
1!
1$
b11 "
#388
0%
0!
0#
0$
b0 "
#389
1$
b1 "
#390
1#
0$
b10 "
#391
1%
1!
1$
b11 "
#392
0%
0!
0#
0$
b0 "
#393
1$
b1 "
#394
1#
0$
b10 "
#395
1%
1!
1$
b11 "
#396
0%
0!
0#
0$
b0 "
#397
1$
b1 "
#398
1#
0$
b10 "
#399
1%
1!
1$
b11 "
#400
0%
0!
0#
0$
b0 "
#401
1$
b1 "
#402
1#
0$
b10 "
#403
1%
1!
1$
b11 "
#404
0%
0!
0#
0$
b0 "
#405
1$
b1 "
#406
1#
0$
b10 "
#407
1%
1!
1$
b11 "
#408
0%
0!
0#
0$
b0 "
#409
1$
b1 "
#410
1#
0$
b10 "
#411
1%
1!
1$
b11 "
#412
0%
0!
0#
0$
b0 "
#413
1$
b1 "
#414
1#
0$
b10 "
#415
1%
1!
1$
b11 "
#416
0%
0!
0#
0$
b0 "
#417
1$
b1 "
#418
1#
0$
b10 "
#419
1%
1!
1$
b11 "
#420
0%
0!
0#
0$
b0 "
#421
1$
b1 "
#422
1#
0$
b10 "
#423
1%
1!
1$
b11 "
#424
0%
0!
0#
0$
b0 "
#425
1$
b1 "
#426
1#
0$
b10 "
#427
1%
1!
1$
b11 "
#428
0%
0!
0#
0$
b0 "
#429
1$
b1 "
#430
1#
0$
b10 "
#431
1%
1!
1$
b11 "
#432
0%
0!
0#
0$
b0 "
#433
1$
b1 "
#434
1#
0$
b10 "
#435
1%
1!
1$
b11 "
#436
0%
0!
0#
0$
b0 "
#437
1$
b1 "
#438
1#
0$
b10 "
#439
1%
1!
1$
b11 "
#440
0%
0!
0#
0$
b0 "
#441
1$
b1 "
#442
1#
0$
b10 "
#443
1%
1!
1$
b11 "
#444
0%
0!
0#
0$
b0 "
#445
1$
b1 "
#446
1#
0$
b10 "
#447
1%
1!
1$
b11 "
#448
0%
0!
0#
0$
b0 "
#449
1$
b1 "
#450
1#
0$
b10 "
#451
1%
1!
1$
b11 "
#452
0%
0!
0#
0$
b0 "
#453
1$
b1 "
#454
1#
0$
b10 "
#455
1%
1!
1$
b11 "
#456
0%
0!
0#
0$
b0 "
#457
1$
b1 "
#458
1#
0$
b10 "
#459
1%
1!
1$
b11 "
#460
0%
0!
0#
0$
b0 "
#461
1$
b1 "
#462
1#
0$
b10 "
#463
1%
1!
1$
b11 "
#464
0%
0!
0#
0$
b0 "
#465
1$
b1 "
#466
1#
0$
b10 "
#467
1%
1!
1$
b11 "
#468
0%
0!
0#
0$
b0 "
#469
1$
b1 "
#470
1#
0$
b10 "
#471
1%
1!
1$
b11 "
#472
0%
0!
0#
0$
b0 "
#473
1$
b1 "
#474
1#
0$
b10 "
#475
1%
1!
1$
b11 "
#476
0%
0!
0#
0$
b0 "
#477
1$
b1 "
#478
1#
0$
b10 "
#479
1%
1!
1$
b11 "
#480
0%
0!
0#
0$
b0 "
#481
1$
b1 "
#482
1#
0$
b10 "
#483
1%
1!
1$
b11 "
#484
0%
0!
0#
0$
b0 "
#485
1$
b1 "
#486
1#
0$
b10 "
#487
1%
1!
1$
b11 "
#488
0%
0!
0#
0$
b0 "
#489
1$
b1 "
#490
1#
0$
b10 "
#491
1%
1!
1$
b11 "
#492
0%
0!
0#
0$
b0 "
#493
1$
b1 "
#494
1#
0$
b10 "
#495
1%
1!
1$
b11 "
#496
0%
0!
0#
0$
b0 "
#497
1$
b1 "
#498
1#
0$
b10 "
#499
1%
1!
1$
b11 "
#500
0%
0!
0#
0$
b0 "
