Flipflops/SR/functional/1/SR_1.v
//Created by Soumik Guha Roy and moral support by the great Morris Mano
module ffSR(s,r,clock,y);
// Without using the RESET signal
	input s,r,clock;
	output y;
	reg y;
	
	initial
		begin
			//This is the initial block
			//this block will be executed only 
			y=1'b0;
		end

		always @(posedge clock)
			begin
				
				if (s == 1'b0 && r == 1'b0) 				//This always block will be executed when inputs are changed
				begin
					y=y;
				end
				else if (s == 1'b0 && r == 1'b1)
				begin
					y=s;
				end
				else if (s == 1'b1 && r == 1'b0)
				begin
					y=s;
				end
				else
				begin
					y=1'bx;
				end
			end
endmodule
//End of the definition of the SR function

Flipflops/SR/functional/1/tb.v
module tb;
	reg [2:0] myData;//S,R,CLOCK
	ffSR mySR(myData[2],myData[1],myData[0],y_out); //module ffSR(s,r,clock,y);
	initial 
		begin
			myData=3'b011;
			$dumpfile("wave.vcd");
			$dumpvars(0,tb);
			#100 $finish;
				
		end

	always
		begin
			#5 myData<=myData+1;
		end
endmodule

Flipflops/SR/functional/1/wave.vcd
$date
	Wed Aug 20 23:54:09 2025
$end
$version
	Icarus Verilog
$end
$timescale
	1s
$end
$scope module tb $end
$var wire 1 ! y_out $end
$var reg 3 " myData [2:0] $end
$scope module mySR $end
$var wire 1 # clock $end
$var wire 1 $ r $end
$var wire 1 % s $end
$var reg 1 ! y $end
$upscope $end
$upscope $end
$enddefinitions $end
#0
$dumpvars
0%
1$
1#
b11 "
0!
$end
#5
1%
0$
0#
b100 "
#10
1!
1#
b101 "
#15
1$
0#
b110 "
#20
x!
1#
b111 "
#25
0%
0$
0#
b0 "
#30
1#
b1 "
#35
1$
0#
b10 "
#40
0!
1#
b11 "
#45
1%
0$
0#
b100 "
#50
1!
1#
b101 "
#55
1$
0#
b110 "
#60
x!
1#
b111 "
#65
0%
0$
0#
b0 "
#70
1#
b1 "
#75
1$
0#
b10 "
#80
0!
1#
b11 "
#85
1%
0$
0#
b100 "
#90
1!
1#
b101 "
#95
1$
0#
b110 "
#100
x!
1#
b111 "
