Basic/AND Behaviour/andGate.v
module andGate(a,b,y);
	input a,b;
	output y;
	reg y;
	
	initial
		begin
			//This is the initial block
			//this block will be executed only 
		end

	always @(a or b )
		begin
			//This always block will be executed when inputs are changed
			if (a == 1'b0 || b == 1'b0)
			begin
				y=1'b0;
			end
			else
			begin
				y=1'b1;
			end
		end
endmodule
//End of the definition of the AND function

Basic/AND Behaviour/tb.v
module tb;
	reg [1:0] myData;
	andGate myAnd(myData[1],myData[0],y_out);
	initial 
		begin
			myData=2'b00;
			$dumpfile("wave.vcd");
			$dumpvars(0,tb);
			#100 $finish;
				
		end

	always
		begin
			#5 myData<=myData+1;
		end
endmodule

Basic/AND Behaviour/wave.vcd
$date
	Wed Aug 20 21:52:35 2025
$end
$version
	Icarus Verilog
$end
$timescale
	1s
$end
$scope module tb $end
$var wire 1 ! y_out $end
$var reg 2 " myData [1:0] $end
$scope module myAnd $end
$var wire 1 # a $end
$var wire 1 $ b $end
$var reg 1 ! y $end
$upscope $end
$upscope $end
$enddefinitions $end
#0
$dumpvars
0$
0#
b0 "
0!
$end
#5
1$
b1 "
#10
1#
0$
b10 "
#15
1!
1$
b11 "
#20
0!
0#
0$
b0 "
#25
1$
b1 "
#30
1#
0$
b10 "
#35
1!
1$
b11 "
#40
0!
0#
0$
b0 "
#45
1$
b1 "
#50
1#
0$
b10 "
#55
1!
1$
b11 "
#60
0!
0#
0$
b0 "
#65
1$
b1 "
#70
1#
0$
b10 "
#75
1!
1$
b11 "
#80
0!
0#
0$
b0 "
#85
1$
b1 "
#90
1#
0$
b10 "
#95
1!
1$
b11 "
#100
0!
0#
0$
b0 "
