counter/counter 1/counter.v
module counter(out,clk,reset);

	parameter WIDTH=8;
	output [WIDTH-1:0] out;
	input clk,reset;

	reg[WIDTH-1:0] out;
	wire clk,reset;

	always @(posedge clk)
		out<=out+1;
	
	always @reset
		if (reset==1)
			assign out=0;
		else
			deassign out;
endmodule

counter/counter 1/tb.v
module tb;
	reg reset=0;
	
	initial begin
		$dumpfile("myoutput.vcd");
		$dumpvars(0,tb);
		
		#15	reset=1;
		
		#10	reset=0;
		//#20	reset=1;
		//#5	reset=0;
		
		#500	$finish;
		
	end
	
	//Make a regular pulsating clock
	reg clk=0;
	always
		#1	clk=!clk;

	wire [7:0] value;
	counter c(value,clk,reset);

endmodule

counter/counter 1/myoutput.vcd
$date
	Thu Jul 12 20:42:08 2018
$end
$version
	Icarus Verilog
$end
$timescale
	1s
$end
$scope module tb $end
$var wire 8 ! value [7:0] $end
$var reg 1 " clk $end
$var reg 1 # reset $end
$scope module c $end
$var wire 1 $ clk $end
$var wire 1 % reset $end
$var reg 8 & out [7:0] $end
$upscope $end
$upscope $end
$enddefinitions $end
#0
$dumpvars
bx &
0%
0$
0#
0"
bx !
$end
#1
1"
1$
#2
0"
0$
#3
1"
1$
#4
0"
0$
#5
1"
1$
#6
0"
0$
#7
1"
1$
#8
0"
0$
#9
1"
1$
#10
0"
0$
#11
1"
1$
#12
0"
0$
#13
1"
1$
#14
0"
0$
#15
b0 &
b0 !
1"
1$
1#
1%
#16
0"
0$
#17
1"
1$
#18
0"
0$
#19
1"
1$
#20
0"
0$
#21
1"
1$
#22
0"
0$
#23
1"
1$
#24
0"
0$
#25
b1 &
b1 !
1"
1$
0#
0%
#26
0"
0$
#27
b10 &
b10 !
1"
1$
#28
0"
0$
#29
b11 &
b11 !
1"
1$
#30
0"
0$
#31
b100 &
b100 !
1"
1$
#32
0"
0$
#33
b101 &
b101 !
1"
1$
#34
0"
0$
#35
b110 &
b110 !
1"
1$
#36
0"
0$
#37
b111 &
b111 !
1"
1$
#38
0"
0$
#39
b1000 &
b1000 !
1"
1$
#40
0"
0$
#41
b1001 &
b1001 !
1"
1$
#42
0"
0$
#43
b1010 &
b1010 !
1"
1$
#44
0"
0$
#45
b1011 &
b1011 !
1"
1$
#46
0"
0$
#47
b1100 &
b1100 !
1"
1$
#48
0"
0$
#49
b1101 &
b1101 !
1"
1$
#50
0"
0$
#51
b1110 &
b1110 !
1"
1$
#52
0"
0$
#53
b1111 &
b1111 !
1"
1$
#54
0"
0$
#55
b10000 &
b10000 !
1"
1$
#56
0"
0$
#57
b10001 &
b10001 !
1"
1$
#58
0"
0$
#59
b10010 &
b10010 !
1"
1$
#60
0"
0$
#61
b10011 &
b10011 !
1"
1$
#62
0"
0$
#63
b10100 &
b10100 !
1"
1$
#64
0"
0$
#65
b10101 &
b10101 !
1"
1$
#66
0"
0$
#67
b10110 &
b10110 !
1"
1$
#68
0"
0$
#69
b10111 &
b10111 !
1"
1$
#70
0"
0$
#71
b11000 &
b11000 !
1"
1$
#72
0"
0$
#73
b11001 &
b11001 !
1"
1$
#74
0"
0$
#75
b11010 &
b11010 !
1"
1$
#76
0"
0$
#77
b11011 &
b11011 !
1"
1$
#78
0"
0$
#79
b11100 &
b11100 !
1"
1$
#80
0"
0$
#81
b11101 &
b11101 !
1"
1$
#82
0"
0$
#83
b11110 &
b11110 !
1"
1$
#84
0"
0$
#85
b11111 &
b11111 !
1"
1$
#86
0"
0$
#87
b100000 &
b100000 !
1"
1$
#88
0"
0$
#89
b100001 &
b100001 !
1"
1$
#90
0"
0$
#91
b100010 &
b100010 !
1"
1$
#92
0"
0$
#93
b100011 &
b100011 !
1"
1$
#94
0"
0$
#95
b100100 &
b100100 !
1"
1$
#96
0"
0$
#97
b100101 &
b100101 !
1"
1$
#98
0"
0$
#99
b100110 &
b100110 !
1"
1$
#100
0"
0$
#101
b100111 &
b100111 !
1"
1$
#102
0"
0$
#103
b101000 &
b101000 !
1"
1$
#104
0"
0$
#105
b101001 &
b101001 !
1"
1$
#106
0"
0$
#107
b101010 &
b101010 !
1"
1$
#108
0"
0$
#109
b101011 &
b101011 !
1"
1$
#110
0"
0$
#111
b101100 &
b101100 !
1"
1$
#112
0"
0$
#113
b101101 &
b101101 !
1"
1$
#114
0"
0$
#115
b101110 &
b101110 !
1"
1$
#116
0"
0$
#117
b101111 &
b101111 !
1"
1$
#118
0"
0$
#119
b110000 &
b110000 !
1"
1$
#120
0"
0$
#121
b110001 &
b110001 !
1"
1$
#122
0"
0$
#123
b110010 &
b110010 !
1"
1$
#124
0"
0$
#125
b110011 &
b110011 !
1"
1$
#126
0"
0$
#127
b110100 &
b110100 !
1"
1$
#128
0"
0$
#129
b110101 &
b110101 !
1"
1$
#130
0"
0$
#131
b110110 &
b110110 !
1"
1$
#132
0"
0$
#133
b110111 &
b110111 !
1"
1$
#134
0"
0$
#135
b111000 &
b111000 !
1"
1$
#136
0"
0$
#137
b111001 &
b111001 !
1"
1$
#138
0"
0$
#139
b111010 &
b111010 !
1"
1$
#140
0"
0$
#141
b111011 &
b111011 !
1"
1$
#142
0"
0$
#143
b111100 &
b111100 !
1"
1$
#144
0"
0$
#145
b111101 &
b111101 !
1"
1$
#146
0"
0$
#147
b111110 &
b111110 !
1"
1$
#148
0"
0$
#149
b111111 &
b111111 !
1"
1$
#150
0"
0$
#151
b1000000 &
b1000000 !
1"
1$
#152
0"
0$
#153
b1000001 &
b1000001 !
1"
1$
#154
0"
0$
#155
b1000010 &
b1000010 !
1"
1$
#156
0"
0$
#157
b1000011 &
b1000011 !
1"
1$
#158
0"
0$
#159
b1000100 &
b1000100 !
1"
1$
#160
0"
0$
#161
b1000101 &
b1000101 !
1"
1$
#162
0"
0$
#163
b1000110 &
b1000110 !
1"
1$
#164
0"
0$
#165
b1000111 &
b1000111 !
1"
1$
#166
0"
0$
#167
b1001000 &
b1001000 !
1"
1$
#168
0"
0$
#169
b1001001 &
b1001001 !
1"
1$
#170
0"
0$
#171
b1001010 &
b1001010 !
1"
1$
#172
0"
0$
#173
b1001011 &
b1001011 !
1"
1$
#174
0"
0$
#175
b1001100 &
b1001100 !
1"
1$
#176
0"
0$
#177
b1001101 &
b1001101 !
1"
1$
#178
0"
0$
#179
b1001110 &
b1001110 !
1"
1$
#180
0"
0$
#181
b1001111 &
b1001111 !
1"
1$
#182
0"
0$
#183
b1010000 &
b1010000 !
1"
1$
#184
0"
0$
#185
b1010001 &
b1010001 !
1"
1$
#186
0"
0$
#187
b1010010 &
b1010010 !
1"
1$
#188
0"
0$
#189
b1010011 &
b1010011 !
1"
1$
#190
0"
0$
#191
b1010100 &
b1010100 !
1"
1$
#192
0"
0$
#193
b1010101 &
b1010101 !
1"
1$
#194
0"
0$
#195
b1010110 &
b1010110 !
1"
1$
#196
0"
0$
#197
b1010111 &
b1010111 !
1"
1$
#198
0"
0$
#199
b1011000 &
b1011000 !
1"
1$
#200
0"
0$
#201
b1011001 &
b1011001 !
1"
1$
#202
0"
0$
#203
b1011010 &
b1011010 !
1"
1$
#204
0"
0$
#205
b1011011 &
b1011011 !
1"
1$
#206
0"
0$
#207
b1011100 &
b1011100 !
1"
1$
#208
0"
0$
#209
b1011101 &
b1011101 !
1"
1$
#210
0"
0$
#211
b1011110 &
b1011110 !
1"
1$
#212
0"
0$
#213
b1011111 &
b1011111 !
1"
1$
#214
0"
0$
#215
b1100000 &
b1100000 !
1"
1$
#216
0"
0$
#217
b1100001 &
b1100001 !
1"
1$
#218
0"
0$
#219
b1100010 &
b1100010 !
1"
1$
#220
0"
0$
#221
b1100011 &
b1100011 !
1"
1$
#222
0"
0$
#223
b1100100 &
b1100100 !
1"
1$
#224
0"
0$
#225
b1100101 &
b1100101 !
1"
1$
#226
0"
0$
#227
b1100110 &
b1100110 !
1"
1$
#228
0"
0$
#229
b1100111 &
b1100111 !
1"
1$
#230
0"
0$
#231
b1101000 &
b1101000 !
1"
1$
#232
0"
0$
#233
b1101001 &
b1101001 !
1"
1$
#234
0"
0$
#235
b1101010 &
b1101010 !
1"
1$
#236
0"
0$
#237
b1101011 &
b1101011 !
1"
1$
#238
0"
0$
#239
b1101100 &
b1101100 !
1"
1$
#240
0"
0$
#241
b1101101 &
b1101101 !
1"
1$
#242
0"
0$
#243
b1101110 &
b1101110 !
1"
1$
#244
0"
0$
#245
b1101111 &
b1101111 !
1"
1$
#246
0"
0$
#247
b1110000 &
b1110000 !
1"
1$
#248
0"
0$
#249
b1110001 &
b1110001 !
1"
1$
#250
0"
0$
#251
b1110010 &
b1110010 !
1"
1$
#252
0"
0$
#253
b1110011 &
b1110011 !
1"
1$
#254
0"
0$
#255
b1110100 &
b1110100 !
1"
1$
#256
0"
0$
#257
b1110101 &
b1110101 !
1"
1$
#258
0"
0$
#259
b1110110 &
b1110110 !
1"
1$
#260
0"
0$
#261
b1110111 &
b1110111 !
1"
1$
#262
0"
0$
#263
b1111000 &
b1111000 !
1"
1$
#264
0"
0$
#265
b1111001 &
b1111001 !
1"
1$
#266
0"
0$
#267
b1111010 &
b1111010 !
1"
1$
#268
0"
0$
#269
b1111011 &
b1111011 !
1"
1$
#270
0"
0$
#271
b1111100 &
b1111100 !
1"
1$
#272
0"
0$
#273
b1111101 &
b1111101 !
1"
1$
#274
0"
0$
#275
b1111110 &
b1111110 !
1"
1$
#276
0"
0$
#277
b1111111 &
b1111111 !
1"
1$
#278
0"
0$
#279
b10000000 &
b10000000 !
1"
1$
#280
0"
0$
#281
b10000001 &
b10000001 !
1"
1$
#282
0"
0$
#283
b10000010 &
b10000010 !
1"
1$
#284
0"
0$
#285
b10000011 &
b10000011 !
1"
1$
#286
0"
0$
#287
b10000100 &
b10000100 !
1"
1$
#288
0"
0$
#289
b10000101 &
b10000101 !
1"
1$
#290
0"
0$
#291
b10000110 &
b10000110 !
1"
1$
#292
0"
0$
#293
b10000111 &
b10000111 !
1"
1$
#294
0"
0$
#295
b10001000 &
b10001000 !
1"
1$
#296
0"
0$
#297
b10001001 &
b10001001 !
1"
1$
#298
0"
0$
#299
b10001010 &
b10001010 !
1"
1$
#300
0"
0$
#301
b10001011 &
b10001011 !
1"
1$
#302
0"
0$
#303
b10001100 &
b10001100 !
1"
1$
#304
0"
0$
#305
b10001101 &
b10001101 !
1"
1$
#306
0"
0$
#307
b10001110 &
b10001110 !
1"
1$
#308
0"
0$
#309
b10001111 &
b10001111 !
1"
1$
#310
0"
0$
#311
b10010000 &
b10010000 !
1"
1$
#312
0"
0$
#313
b10010001 &
b10010001 !
1"
1$
#314
0"
0$
#315
b10010010 &
b10010010 !
1"
1$
#316
0"
0$
#317
b10010011 &
b10010011 !
1"
1$
#318
0"
0$
#319
b10010100 &
b10010100 !
1"
1$
#320
0"
0$
#321
b10010101 &
b10010101 !
1"
1$
#322
0"
0$
#323
b10010110 &
b10010110 !
1"
1$
#324
0"
0$
#325
b10010111 &
b10010111 !
1"
1$
#326
0"
0$
#327
b10011000 &
b10011000 !
1"
1$
#328
0"
0$
#329
b10011001 &
b10011001 !
1"
1$
#330
0"
0$
#331
b10011010 &
b10011010 !
1"
1$
#332
0"
0$
#333
b10011011 &
b10011011 !
1"
1$
#334
0"
0$
#335
b10011100 &
b10011100 !
1"
1$
#336
0"
0$
#337
b10011101 &
b10011101 !
1"
1$
#338
0"
0$
#339
b10011110 &
b10011110 !
1"
1$
#340
0"
0$
#341
b10011111 &
b10011111 !
1"
1$
#342
0"
0$
#343
b10100000 &
b10100000 !
1"
1$
#344
0"
0$
#345
b10100001 &
b10100001 !
1"
1$
#346
0"
0$
#347
b10100010 &
b10100010 !
1"
1$
#348
0"
0$
#349
b10100011 &
b10100011 !
1"
1$
#350
0"
0$
#351
b10100100 &
b10100100 !
1"
1$
#352
0"
0$
#353
b10100101 &
b10100101 !
1"
1$
#354
0"
0$
#355
b10100110 &
b10100110 !
1"
1$
#356
0"
0$
#357
b10100111 &
b10100111 !
1"
1$
#358
0"
0$
#359
b10101000 &
b10101000 !
1"
1$
#360
0"
0$
#361
b10101001 &
b10101001 !
1"
1$
#362
0"
0$
#363
b10101010 &
b10101010 !
1"
1$
#364
0"
0$
#365
b10101011 &
b10101011 !
1"
1$
#366
0"
0$
#367
b10101100 &
b10101100 !
1"
1$
#368
0"
0$
#369
b10101101 &
b10101101 !
1"
1$
#370
0"
0$
#371
b10101110 &
b10101110 !
1"
1$
#372
0"
0$
#373
b10101111 &
b10101111 !
1"
1$
#374
0"
0$
#375
b10110000 &
b10110000 !
1"
1$
#376
0"
0$
#377
b10110001 &
b10110001 !
1"
1$
#378
0"
0$
#379
b10110010 &
b10110010 !
1"
1$
#380
0"
0$
#381
b10110011 &
b10110011 !
1"
1$
#382
0"
0$
#383
b10110100 &
b10110100 !
1"
1$
#384
0"
0$
#385
b10110101 &
b10110101 !
1"
1$
#386
0"
0$
#387
b10110110 &
b10110110 !
1"
1$
#388
0"
0$
#389
b10110111 &
b10110111 !
1"
1$
#390
0"
0$
#391
b10111000 &
b10111000 !
1"
1$
#392
0"
0$
#393
b10111001 &
b10111001 !
1"
1$
#394
0"
0$
#395
b10111010 &
b10111010 !
1"
1$
#396
0"
0$
#397
b10111011 &
b10111011 !
1"
1$
#398
0"
0$
#399
b10111100 &
b10111100 !
1"
1$
#400
0"
0$
#401
b10111101 &
b10111101 !
1"
1$
#402
0"
0$
#403
b10111110 &
b10111110 !
1"
1$
#404
0"
0$
#405
b10111111 &
b10111111 !
1"
1$
#406
0"
0$
#407
b11000000 &
b11000000 !
1"
1$
#408
0"
0$
#409
b11000001 &
b11000001 !
1"
1$
#410
0"
0$
#411
b11000010 &
b11000010 !
1"
1$
#412
0"
0$
#413
b11000011 &
b11000011 !
1"
1$
#414
0"
0$
#415
b11000100 &
b11000100 !
1"
1$
#416
0"
0$
#417
b11000101 &
b11000101 !
1"
1$
#418
0"
0$
#419
b11000110 &
b11000110 !
1"
1$
#420
0"
0$
#421
b11000111 &
b11000111 !
1"
1$
#422
0"
0$
#423
b11001000 &
b11001000 !
1"
1$
#424
0"
0$
#425
b11001001 &
b11001001 !
1"
1$
#426
0"
0$
#427
b11001010 &
b11001010 !
1"
1$
#428
0"
0$
#429
b11001011 &
b11001011 !
1"
1$
#430
0"
0$
#431
b11001100 &
b11001100 !
1"
1$
#432
0"
0$
#433
b11001101 &
b11001101 !
1"
1$
#434
0"
0$
#435
b11001110 &
b11001110 !
1"
1$
#436
0"
0$
#437
b11001111 &
b11001111 !
1"
1$
#438
0"
0$
#439
b11010000 &
b11010000 !
1"
1$
#440
0"
0$
#441
b11010001 &
b11010001 !
1"
1$
#442
0"
0$
#443
b11010010 &
b11010010 !
1"
1$
#444
0"
0$
#445
b11010011 &
b11010011 !
1"
1$
#446
0"
0$
#447
b11010100 &
b11010100 !
1"
1$
#448
0"
0$
#449
b11010101 &
b11010101 !
1"
1$
#450
0"
0$
#451
b11010110 &
b11010110 !
1"
1$
#452
0"
0$
#453
b11010111 &
b11010111 !
1"
1$
#454
0"
0$
#455
b11011000 &
b11011000 !
1"
1$
#456
0"
0$
#457
b11011001 &
b11011001 !
1"
1$
#458
0"
0$
#459
b11011010 &
b11011010 !
1"
1$
#460
0"
0$
#461
b11011011 &
b11011011 !
1"
1$
#462
0"
0$
#463
b11011100 &
b11011100 !
1"
1$
#464
0"
0$
#465
b11011101 &
b11011101 !
1"
1$
#466
0"
0$
#467
b11011110 &
b11011110 !
1"
1$
#468
0"
0$
#469
b11011111 &
b11011111 !
1"
1$
#470
0"
0$
#471
b11100000 &
b11100000 !
1"
1$
#472
0"
0$
#473
b11100001 &
b11100001 !
1"
1$
#474
0"
0$
#475
b11100010 &
b11100010 !
1"
1$
#476
0"
0$
#477
b11100011 &
b11100011 !
1"
1$
#478
0"
0$
#479
b11100100 &
b11100100 !
1"
1$
#480
0"
0$
#481
b11100101 &
b11100101 !
1"
1$
#482
0"
0$
#483
b11100110 &
b11100110 !
1"
1$
#484
0"
0$
#485
b11100111 &
b11100111 !
1"
1$
#486
0"
0$
#487
b11101000 &
b11101000 !
1"
1$
#488
0"
0$
#489
b11101001 &
b11101001 !
1"
1$
#490
0"
0$
#491
b11101010 &
b11101010 !
1"
1$
#492
0"
0$
#493
b11101011 &
b11101011 !
1"
1$
#494
0"
0$
#495
b11101100 &
b11101100 !
1"
1$
#496
0"
0$
#497
b11101101 &
b11101101 !
1"
1$
#498
0"
0$
#499
b11101110 &
b11101110 !
1"
1$
#500
0"
0$
#501
b11101111 &
b11101111 !
1"
1$
#502
0"
0$
#503
b11110000 &
b11110000 !
1"
1$
#504
0"
0$
#505
b11110001 &
b11110001 !
1"
1$
#506
0"
0$
#507
b11110010 &
b11110010 !
1"
1$
#508
0"
0$
#509
b11110011 &
b11110011 !
1"
1$
#510
0"
0$
#511
b11110100 &
b11110100 !
1"
1$
#512
0"
0$
#513
b11110101 &
b11110101 !
1"
1$
#514
0"
0$
#515
b11110110 &
b11110110 !
1"
1$
#516
0"
0$
#517
b11110111 &
b11110111 !
1"
1$
#518
0"
0$
#519
b11111000 &
b11111000 !
1"
1$
#520
0"
0$
#521
b11111001 &
b11111001 !
1"
1$
#522
0"
0$
#523
b11111010 &
b11111010 !
1"
1$
#524
0"
0$
#525
b11111011 &
b11111011 !
1"
1$
