Flipflops/JK/functional/2/JK.v
//Created by Soumik Guha Roy and moral support by the great Morris Mano
module ffJK(j,k,clock,reset,y,y_bar);
// Using the RESET signal
	input j,k,clock,reset;
	output y,y_bar;
	reg y,y_bar;
	
	initial
		begin
			//This is the initial block
			//this block will be executed only 
			y=1'bx;
			y_bar=1'bx;
			$display("[SGR]Output initialized..");
		end
	always @(posedge reset)
			begin
				if (reset == 1'b1) //My assumption
				begin
					y=1'b0;
					y_bar=1'b1;
				end
			end

	always @(posedge clock)
			begin
				$display("Hello... S:");	
				
				if (j == 1'b0 && k == 1'b0) 				//This always block will be executed when inputs are changed
				begin
					//y<=y;
				end
				else if (j == 1'b0 && k == 1'b1)
				begin
					y<=1'b0;
					y_bar<=1'b1;
				end
				else if (j == 1'b1 && k == 1'b0)
				begin
					y<=1'b1;
					y_bar<=1'b0;
				end
				else if (j == 1'b1 && k == 1'b1)
				begin
					y=!y;
					y_bar=y;
				end
			end
endmodule
//End of the functional/behavioral definition of the JK function

Flipflops/JK/functional/2/tb.v
module tb;
	reg [3:0] myData;//J,K,CLOCK,Reset
	ffJK myJK(myData[3],myData[2],myData[1],myData[0],y_out,Y_out_bar); //module ffJK(j,k,clock,reset,y);
	initial 
		begin
			myData=4'b0000;
			$dumpfile("wave.vcd");
			$dumpvars(0,tb);
			#100 $finish;
				
		end

	always
		begin
			#5 myData<=myData+1;
			//#5 myData[1]<= !myData[1];
			//#5 myData[2]<= !myData[2];
			//#5 myData[3]<= !myData[3];
		end
endmodule

Flipflops/JK/functional/2/wave.vcd
$date
	Tue Aug 26 00:14:05 2025
$end
$version
	Icarus Verilog
$end
$timescale
	1s
$end
$scope module tb $end
$var wire 1 ! y_out $end
$var wire 1 " Y_out_bar $end
$var reg 4 # myData [3:0] $end
$scope module myJK $end
$var wire 1 $ clock $end
$var wire 1 % j $end
$var wire 1 & k $end
$var wire 1 ' reset $end
$var reg 1 ! y $end
$var reg 1 " y_bar $end
$upscope $end
$upscope $end
$enddefinitions $end
#0
$dumpvars
0'
0&
0%
0$
b0 #
x"
x!
$end
#5
1"
0!
1'
b1 #
#10
1$
0'
b10 #
#15
1'
b11 #
#20
1&
0$
0'
b100 #
#25
1'
b101 #
#30
1$
0'
b110 #
#35
1'
b111 #
#40
1%
0&
0$
0'
b1000 #
#45
1'
b1001 #
#50
0"
1!
1$
0'
b1010 #
#55
1"
0!
1'
b1011 #
#60
1&
0$
0'
b1100 #
#65
1'
b1101 #
#70
1!
1$
0'
b1110 #
#75
0!
1'
b1111 #
#80
0%
0&
0$
0'
b0 #
#85
1'
b1 #
#90
1$
0'
b10 #
#95
1'
b11 #
#100
1&
0$
0'
b100 #
