mux/mux 3/mux.v
//THIS IS A 4x1 MUX WITH  ENABLE INPUT
//CREATED BY SOUMIK GUHA ROY
module mux(I0,I1,I2,I3,s1,s0,Enable,y);
	input I0,I1,I2,I3,s1,s0,Enable;
	output y;
	reg y;
	always @( I0 or I1 or I2 or I3 or s1 or s0 or Enable)	
	begin
		if (Enable ==1 )
		begin
			if (s1==0 && s0==0 )
				y<=I0;
			else if(s1==0 && s0==1)
				y<=I1;
			else if(s1==1 && s0==0)
				y<=I2;
			else
				y<=I3;
		end
		else
			y=0;

	end
endmodule

Adder/Full_Adder/behavioral/myFA.v
//This module simulates Full adder operation using behavioral fashion
//Created by Soumik Guha Roy
module myFA(a,b,cin,cout,sum);
	input a,b,cin;
	output cout,sum;
	reg cout,sum;
	
	always @(a or b or cin )
	begin
		sum=(a^b^cin);
		cout=(a&b)|(cin&(a^b));
	end
endmodule

4_Bit-Arithmetic_Unit/arith_4_bit.v
module arith_4_bit (cin,s2,s1,i,j,sum,carryout);
	input cin,s2,s1;
	input [3:0] i;
	input [3:0] j;
	output [3:0] sum;
	output carryout;
	
	myFA FA_1(i[0],y1,cin,c1,sum[0]);
	myFA FA_2(i[1],y2,c1,c2,sum[1]);
	myFA FA_3(i[2],y3,c2,c3,sum[2]);
	myFA FA_4(i[3],y4,c3,c4,sum[3]);

	mux MUX_1(j[0],!j[0],1'b0,1'b1,s2,s1,1'b1,y1);
	mux MUX_2(j[1],!j[1],1'b0,1'b1,s2,s1,1'b1,y2);
	mux MUX_3(j[2],!j[2],1'b0,1'b1,s2,s1,1'b1,y3);
	mux MUX_4(j[3],!j[3],1'b0,1'b1,s2,s1,1'b1,y4);

endmodule

4_Bit-Arithmetic_Unit/tb.v
module tb;

	reg [10:0] myData;
	wire [3:0] sum;
	arith_4_bit unit(myData[10],myData[9],myData[8],myData[7:4],myData[3:0],sum[3:0],cout);
	
	initial
		begin
			myData=11'b0;
			$dumpfile ("wave.vcd");
			$dumpvars(1,tb);
			#5000 $finish;
		end

	always 
		begin
			#5 myData<=myData+1;
		end
	
endmodule

4_Bit-Arithmetic_Unit/wave.vcd
$date
	Wed Oct 31 12:30:39 2018
$end
$version
	Icarus Verilog
$end
$timescale
	1s
$end
$scope module tb $end
$var wire 1 ! cout $end
$var wire 4 " sum [3:0] $end
$var reg 11 # myData [10:0] $end
$upscope $end
$enddefinitions $end
#0
$dumpvars
b0 #
b0 "
z!
$end
#5
b1 "
b1 #
#10
b10 "
b10 #
#15
b11 "
b11 #
#20
b100 "
b100 #
#25
b101 "
b101 #
#30
b110 "
b110 #
#35
b111 "
b111 #
#40
b1000 "
b1000 #
#45
b1001 "
b1001 #
#50
b1010 "
b1010 #
#55
b1011 "
b1011 #
#60
b1100 "
b1100 #
#65
b1101 "
b1101 #
#70
b1110 "
b1110 #
#75
b1111 "
b1111 #
#80
b1 "
b10000 #
#85
b10 "
b10001 #
#90
b11 "
b10010 #
#95
b100 "
b10011 #
#100
b101 "
b10100 #
#105
b110 "
b10101 #
#110
b111 "
b10110 #
#115
b1000 "
b10111 #
#120
b1001 "
b11000 #
#125
b1010 "
b11001 #
#130
b1011 "
b11010 #
#135
b1100 "
b11011 #
#140
b1101 "
b11100 #
#145
b1110 "
b11101 #
#150
b1111 "
b11110 #
#155
b0 "
b11111 #
#160
b10 "
b100000 #
#165
b11 "
b100001 #
#170
b100 "
b100010 #
#175
b101 "
b100011 #
#180
b110 "
b100100 #
#185
b111 "
b100101 #
#190
b1000 "
b100110 #
#195
b1001 "
b100111 #
#200
b1010 "
b101000 #
#205
b1011 "
b101001 #
#210
b1100 "
b101010 #
#215
b1101 "
b101011 #
#220
b1110 "
b101100 #
#225
b1111 "
b101101 #
#230
b0 "
b101110 #
#235
b1 "
b101111 #
#240
b11 "
b110000 #
#245
b100 "
b110001 #
#250
b101 "
b110010 #
#255
b110 "
b110011 #
#260
b111 "
b110100 #
#265
b1000 "
b110101 #
#270
b1001 "
b110110 #
#275
b1010 "
b110111 #
#280
b1011 "
b111000 #
#285
b1100 "
b111001 #
#290
b1101 "
b111010 #
#295
b1110 "
b111011 #
#300
b1111 "
b111100 #
#305
b0 "
b111101 #
#310
b1 "
b111110 #
#315
b10 "
b111111 #
#320
b100 "
b1000000 #
#325
b101 "
b1000001 #
#330
b110 "
b1000010 #
#335
b111 "
b1000011 #
#340
b1000 "
b1000100 #
#345
b1001 "
b1000101 #
#350
b1010 "
b1000110 #
#355
b1011 "
b1000111 #
#360
b1100 "
b1001000 #
#365
b1101 "
b1001001 #
#370
b1110 "
b1001010 #
#375
b1111 "
b1001011 #
#380
b0 "
b1001100 #
#385
b1 "
b1001101 #
#390
b10 "
b1001110 #
#395
b11 "
b1001111 #
#400
b101 "
b1010000 #
#405
b110 "
b1010001 #
#410
b111 "
b1010010 #
#415
b1000 "
b1010011 #
#420
b1001 "
b1010100 #
#425
b1010 "
b1010101 #
#430
b1011 "
b1010110 #
#435
b1100 "
b1010111 #
#440
b1101 "
b1011000 #
#445
b1110 "
b1011001 #
#450
b1111 "
b1011010 #
#455
b0 "
b1011011 #
#460
b1 "
b1011100 #
#465
b10 "
b1011101 #
#470
b11 "
b1011110 #
#475
b100 "
b1011111 #
#480
b110 "
b1100000 #
#485
b111 "
b1100001 #
#490
b1000 "
b1100010 #
#495
b1001 "
b1100011 #
#500
b1010 "
b1100100 #
#505
b1011 "
b1100101 #
#510
b1100 "
b1100110 #
#515
b1101 "
b1100111 #
#520
b1110 "
b1101000 #
#525
b1111 "
b1101001 #
#530
b0 "
b1101010 #
#535
b1 "
b1101011 #
#540
b10 "
b1101100 #
#545
b11 "
b1101101 #
#550
b100 "
b1101110 #
#555
b101 "
b1101111 #
#560
b111 "
b1110000 #
#565
b1000 "
b1110001 #
#570
b1001 "
b1110010 #
#575
b1010 "
b1110011 #
#580
b1011 "
b1110100 #
#585
b1100 "
b1110101 #
#590
b1101 "
b1110110 #
#595
b1110 "
b1110111 #
#600
b1111 "
b1111000 #
#605
b0 "
b1111001 #
#610
b1 "
b1111010 #
#615
b10 "
b1111011 #
#620
b11 "
b1111100 #
#625
b100 "
b1111101 #
#630
b101 "
b1111110 #
#635
b110 "
b1111111 #
#640
b1000 "
b10000000 #
#645
b1001 "
b10000001 #
#650
b1010 "
b10000010 #
#655
b1011 "
b10000011 #
#660
b1100 "
b10000100 #
#665
b1101 "
b10000101 #
#670
b1110 "
b10000110 #
#675
b1111 "
b10000111 #
#680
b0 "
b10001000 #
#685
b1 "
b10001001 #
#690
b10 "
b10001010 #
#695
b11 "
b10001011 #
#700
b100 "
b10001100 #
#705
b101 "
b10001101 #
#710
b110 "
b10001110 #
#715
b111 "
b10001111 #
#720
b1001 "
b10010000 #
#725
b1010 "
b10010001 #
#730
b1011 "
b10010010 #
#735
b1100 "
b10010011 #
#740
b1101 "
b10010100 #
#745
b1110 "
b10010101 #
#750
b1111 "
b10010110 #
#755
b0 "
b10010111 #
#760
b1 "
b10011000 #
#765
b10 "
b10011001 #
#770
b11 "
b10011010 #
#775
b100 "
b10011011 #
#780
b101 "
b10011100 #
#785
b110 "
b10011101 #
#790
b111 "
b10011110 #
#795
b1000 "
b10011111 #
#800
b1010 "
b10100000 #
#805
b1011 "
b10100001 #
#810
b1100 "
b10100010 #
#815
b1101 "
b10100011 #
#820
b1110 "
b10100100 #
#825
b1111 "
b10100101 #
#830
b0 "
b10100110 #
#835
b1 "
b10100111 #
#840
b10 "
b10101000 #
#845
b11 "
b10101001 #
#850
b100 "
b10101010 #
#855
b101 "
b10101011 #
#860
b110 "
b10101100 #
#865
b111 "
b10101101 #
#870
b1000 "
b10101110 #
#875
b1001 "
b10101111 #
#880
b1011 "
b10110000 #
#885
b1100 "
b10110001 #
#890
b1101 "
b10110010 #
#895
b1110 "
b10110011 #
#900
b1111 "
b10110100 #
#905
b0 "
b10110101 #
#910
b1 "
b10110110 #
#915
b10 "
b10110111 #
#920
b11 "
b10111000 #
#925
b100 "
b10111001 #
#930
b101 "
b10111010 #
#935
b110 "
b10111011 #
#940
b111 "
b10111100 #
#945
b1000 "
b10111101 #
#950
b1001 "
b10111110 #
#955
b1010 "
b10111111 #
#960
b1100 "
b11000000 #
#965
b1101 "
b11000001 #
#970
b1110 "
b11000010 #
#975
b1111 "
b11000011 #
#980
b0 "
b11000100 #
#985
b1 "
b11000101 #
#990
b10 "
b11000110 #
#995
b11 "
b11000111 #
#1000
b100 "
b11001000 #
#1005
b101 "
b11001001 #
#1010
b110 "
b11001010 #
#1015
b111 "
b11001011 #
#1020
b1000 "
b11001100 #
#1025
b1001 "
b11001101 #
#1030
b1010 "
b11001110 #
#1035
b1011 "
b11001111 #
#1040
b1101 "
b11010000 #
#1045
b1110 "
b11010001 #
#1050
b1111 "
b11010010 #
#1055
b0 "
b11010011 #
#1060
b1 "
b11010100 #
#1065
b10 "
b11010101 #
#1070
b11 "
b11010110 #
#1075
b100 "
b11010111 #
#1080
b101 "
b11011000 #
#1085
b110 "
b11011001 #
#1090
b111 "
b11011010 #
#1095
b1000 "
b11011011 #
#1100
b1001 "
b11011100 #
#1105
b1010 "
b11011101 #
#1110
b1011 "
b11011110 #
#1115
b1100 "
b11011111 #
#1120
b1110 "
b11100000 #
#1125
b1111 "
b11100001 #
#1130
b0 "
b11100010 #
#1135
b1 "
b11100011 #
#1140
b10 "
b11100100 #
#1145
b11 "
b11100101 #
#1150
b100 "
b11100110 #
#1155
b101 "
b11100111 #
#1160
b110 "
b11101000 #
#1165
b111 "
b11101001 #
#1170
b1000 "
b11101010 #
#1175
b1001 "
b11101011 #
#1180
b1010 "
b11101100 #
#1185
b1011 "
b11101101 #
#1190
b1100 "
b11101110 #
#1195
b1101 "
b11101111 #
#1200
b1111 "
b11110000 #
#1205
b0 "
b11110001 #
#1210
b1 "
b11110010 #
#1215
b10 "
b11110011 #
#1220
b11 "
b11110100 #
#1225
b100 "
b11110101 #
#1230
b101 "
b11110110 #
#1235
b110 "
b11110111 #
#1240
b111 "
b11111000 #
#1245
b1000 "
b11111001 #
#1250
b1001 "
b11111010 #
#1255
b1010 "
b11111011 #
#1260
b1011 "
b11111100 #
#1265
b1100 "
b11111101 #
#1270
b1101 "
b11111110 #
#1275
b1110 "
b11111111 #
#1280
b1111 "
b100000000 #
#1285
b1110 "
b100000001 #
#1290
b1101 "
b100000010 #
#1295
b1100 "
b100000011 #
#1300
b1011 "
b100000100 #
#1305
b1010 "
b100000101 #
#1310
b1001 "
b100000110 #
#1315
b1000 "
b100000111 #
#1320
b111 "
b100001000 #
#1325
b110 "
b100001001 #
#1330
b101 "
b100001010 #
#1335
b100 "
b100001011 #
#1340
b11 "
b100001100 #
#1345
b10 "
b100001101 #
#1350
b1 "
b100001110 #
#1355
b0 "
b100001111 #
#1360
b0 "
b100010000 #
#1365
b1111 "
b100010001 #
#1370
b1110 "
b100010010 #
#1375
b1101 "
b100010011 #
#1380
b1100 "
b100010100 #
#1385
b1011 "
b100010101 #
#1390
b1010 "
b100010110 #
#1395
b1001 "
b100010111 #
#1400
b1000 "
b100011000 #
#1405
b111 "
b100011001 #
#1410
b110 "
b100011010 #
#1415
b101 "
b100011011 #
#1420
b100 "
b100011100 #
#1425
b11 "
b100011101 #
#1430
b10 "
b100011110 #
#1435
b1 "
b100011111 #
#1440
b1 "
b100100000 #
#1445
b0 "
b100100001 #
#1450
b1111 "
b100100010 #
#1455
b1110 "
b100100011 #
#1460
b1101 "
b100100100 #
#1465
b1100 "
b100100101 #
#1470
b1011 "
b100100110 #
#1475
b1010 "
b100100111 #
#1480
b1001 "
b100101000 #
#1485
b1000 "
b100101001 #
#1490
b111 "
b100101010 #
#1495
b110 "
b100101011 #
#1500
b101 "
b100101100 #
#1505
b100 "
b100101101 #
#1510
b11 "
b100101110 #
#1515
b10 "
b100101111 #
#1520
b10 "
b100110000 #
#1525
b1 "
b100110001 #
#1530
b0 "
b100110010 #
#1535
b1111 "
b100110011 #
#1540
b1110 "
b100110100 #
#1545
b1101 "
b100110101 #
#1550
b1100 "
b100110110 #
#1555
b1011 "
b100110111 #
#1560
b1010 "
b100111000 #
#1565
b1001 "
b100111001 #
#1570
b1000 "
b100111010 #
#1575
b111 "
b100111011 #
#1580
b110 "
b100111100 #
#1585
b101 "
b100111101 #
#1590
b100 "
b100111110 #
#1595
b11 "
b100111111 #
#1600
b11 "
b101000000 #
#1605
b10 "
b101000001 #
#1610
b1 "
b101000010 #
#1615
b0 "
b101000011 #
#1620
b1111 "
b101000100 #
#1625
b1110 "
b101000101 #
#1630
b1101 "
b101000110 #
#1635
b1100 "
b101000111 #
#1640
b1011 "
b101001000 #
#1645
b1010 "
b101001001 #
#1650
b1001 "
b101001010 #
#1655
b1000 "
b101001011 #
#1660
b111 "
b101001100 #
#1665
b110 "
b101001101 #
#1670
b101 "
b101001110 #
#1675
b100 "
b101001111 #
#1680
b100 "
b101010000 #
#1685
b11 "
b101010001 #
#1690
b10 "
b101010010 #
#1695
b1 "
b101010011 #
#1700
b0 "
b101010100 #
#1705
b1111 "
b101010101 #
#1710
b1110 "
b101010110 #
#1715
b1101 "
b101010111 #
#1720
b1100 "
b101011000 #
#1725
b1011 "
b101011001 #
#1730
b1010 "
b101011010 #
#1735
b1001 "
b101011011 #
#1740
b1000 "
b101011100 #
#1745
b111 "
b101011101 #
#1750
b110 "
b101011110 #
#1755
b101 "
b101011111 #
#1760
b101 "
b101100000 #
#1765
b100 "
b101100001 #
#1770
b11 "
b101100010 #
#1775
b10 "
b101100011 #
#1780
b1 "
b101100100 #
#1785
b0 "
b101100101 #
#1790
b1111 "
b101100110 #
#1795
b1110 "
b101100111 #
#1800
b1101 "
b101101000 #
#1805
b1100 "
b101101001 #
#1810
b1011 "
b101101010 #
#1815
b1010 "
b101101011 #
#1820
b1001 "
b101101100 #
#1825
b1000 "
b101101101 #
#1830
b111 "
b101101110 #
#1835
b110 "
b101101111 #
#1840
b110 "
b101110000 #
#1845
b101 "
b101110001 #
#1850
b100 "
b101110010 #
#1855
b11 "
b101110011 #
#1860
b10 "
b101110100 #
#1865
b1 "
b101110101 #
#1870
b0 "
b101110110 #
#1875
b1111 "
b101110111 #
#1880
b1110 "
b101111000 #
#1885
b1101 "
b101111001 #
#1890
b1100 "
b101111010 #
#1895
b1011 "
b101111011 #
#1900
b1010 "
b101111100 #
#1905
b1001 "
b101111101 #
#1910
b1000 "
b101111110 #
#1915
b111 "
b101111111 #
#1920
b111 "
b110000000 #
#1925
b110 "
b110000001 #
#1930
b101 "
b110000010 #
#1935
b100 "
b110000011 #
#1940
b11 "
b110000100 #
#1945
b10 "
b110000101 #
#1950
b1 "
b110000110 #
#1955
b0 "
b110000111 #
#1960
b1111 "
b110001000 #
#1965
b1110 "
b110001001 #
#1970
b1101 "
b110001010 #
#1975
b1100 "
b110001011 #
#1980
b1011 "
b110001100 #
#1985
b1010 "
b110001101 #
#1990
b1001 "
b110001110 #
#1995
b1000 "
b110001111 #
#2000
b1000 "
b110010000 #
#2005
b111 "
b110010001 #
#2010
b110 "
b110010010 #
#2015
b101 "
b110010011 #
#2020
b100 "
b110010100 #
#2025
b11 "
b110010101 #
#2030
b10 "
b110010110 #
#2035
b1 "
b110010111 #
#2040
b0 "
b110011000 #
#2045
b1111 "
b110011001 #
#2050
b1110 "
b110011010 #
#2055
b1101 "
b110011011 #
#2060
b1100 "
b110011100 #
#2065
b1011 "
b110011101 #
#2070
b1010 "
b110011110 #
#2075
b1001 "
b110011111 #
#2080
b1001 "
b110100000 #
#2085
b1000 "
b110100001 #
#2090
b111 "
b110100010 #
#2095
b110 "
b110100011 #
#2100
b101 "
b110100100 #
#2105
b100 "
b110100101 #
#2110
b11 "
b110100110 #
#2115
b10 "
b110100111 #
#2120
b1 "
b110101000 #
#2125
b0 "
b110101001 #
#2130
b1111 "
b110101010 #
#2135
b1110 "
b110101011 #
#2140
b1101 "
b110101100 #
#2145
b1100 "
b110101101 #
#2150
b1011 "
b110101110 #
#2155
b1010 "
b110101111 #
#2160
b1010 "
b110110000 #
#2165
b1001 "
b110110001 #
#2170
b1000 "
b110110010 #
#2175
b111 "
b110110011 #
#2180
b110 "
b110110100 #
#2185
b101 "
b110110101 #
#2190
b100 "
b110110110 #
#2195
b11 "
b110110111 #
#2200
b10 "
b110111000 #
#2205
b1 "
b110111001 #
#2210
b0 "
b110111010 #
#2215
b1111 "
b110111011 #
#2220
b1110 "
b110111100 #
#2225
b1101 "
b110111101 #
#2230
b1100 "
b110111110 #
#2235
b1011 "
b110111111 #
#2240
b1011 "
b111000000 #
#2245
b1010 "
b111000001 #
#2250
b1001 "
b111000010 #
#2255
b1000 "
b111000011 #
#2260
b111 "
b111000100 #
#2265
b110 "
b111000101 #
#2270
b101 "
b111000110 #
#2275
b100 "
b111000111 #
#2280
b11 "
b111001000 #
#2285
b10 "
b111001001 #
#2290
b1 "
b111001010 #
#2295
b0 "
b111001011 #
#2300
b1111 "
b111001100 #
#2305
b1110 "
b111001101 #
#2310
b1101 "
b111001110 #
#2315
b1100 "
b111001111 #
#2320
b1100 "
b111010000 #
#2325
b1011 "
b111010001 #
#2330
b1010 "
b111010010 #
#2335
b1001 "
b111010011 #
#2340
b1000 "
b111010100 #
#2345
b111 "
b111010101 #
#2350
b110 "
b111010110 #
#2355
b101 "
b111010111 #
#2360
b100 "
b111011000 #
#2365
b11 "
b111011001 #
#2370
b10 "
b111011010 #
#2375
b1 "
b111011011 #
#2380
b0 "
b111011100 #
#2385
b1111 "
b111011101 #
#2390
b1110 "
b111011110 #
#2395
b1101 "
b111011111 #
#2400
b1101 "
b111100000 #
#2405
b1100 "
b111100001 #
#2410
b1011 "
b111100010 #
#2415
b1010 "
b111100011 #
#2420
b1001 "
b111100100 #
#2425
b1000 "
b111100101 #
#2430
b111 "
b111100110 #
#2435
b110 "
b111100111 #
#2440
b101 "
b111101000 #
#2445
b100 "
b111101001 #
#2450
b11 "
b111101010 #
#2455
b10 "
b111101011 #
#2460
b1 "
b111101100 #
#2465
b0 "
b111101101 #
#2470
b1111 "
b111101110 #
#2475
b1110 "
b111101111 #
#2480
b1110 "
b111110000 #
#2485
b1101 "
b111110001 #
#2490
b1100 "
b111110010 #
#2495
b1011 "
b111110011 #
#2500
b1010 "
b111110100 #
#2505
b1001 "
b111110101 #
#2510
b1000 "
b111110110 #
#2515
b111 "
b111110111 #
#2520
b110 "
b111111000 #
#2525
b101 "
b111111001 #
#2530
b100 "
b111111010 #
#2535
b11 "
b111111011 #
#2540
b10 "
b111111100 #
#2545
b1 "
b111111101 #
#2550
b0 "
b111111110 #
#2555
b1111 "
b111111111 #
#2560
b0 "
b1000000000 #
#2565
b1000000001 #
#2570
b1000000010 #
#2575
b1000000011 #
#2580
b1000000100 #
#2585
b1000000101 #
#2590
b1000000110 #
#2595
b1000000111 #
#2600
b1000001000 #
#2605
b1000001001 #
#2610
b1000001010 #
#2615
b1000001011 #
#2620
b1000001100 #
#2625
b1000001101 #
#2630
b1000001110 #
#2635
b1000001111 #
#2640
b1 "
b1000010000 #
#2645
b1000010001 #
#2650
b1000010010 #
#2655
b1000010011 #
#2660
b1000010100 #
#2665
b1000010101 #
#2670
b1000010110 #
#2675
b1000010111 #
#2680
b1000011000 #
#2685
b1000011001 #
#2690
b1000011010 #
#2695
b1000011011 #
#2700
b1000011100 #
#2705
b1000011101 #
#2710
b1000011110 #
#2715
b1000011111 #
#2720
b10 "
b1000100000 #
#2725
b1000100001 #
#2730
b1000100010 #
#2735
b1000100011 #
#2740
b1000100100 #
#2745
b1000100101 #
#2750
b1000100110 #
#2755
b1000100111 #
#2760
b1000101000 #
#2765
b1000101001 #
#2770
b1000101010 #
#2775
b1000101011 #
#2780
b1000101100 #
#2785
b1000101101 #
#2790
b1000101110 #
#2795
b1000101111 #
#2800
b11 "
b1000110000 #
#2805
b1000110001 #
#2810
b1000110010 #
#2815
b1000110011 #
#2820
b1000110100 #
#2825
b1000110101 #
#2830
b1000110110 #
#2835
b1000110111 #
#2840
b1000111000 #
#2845
b1000111001 #
#2850
b1000111010 #
#2855
b1000111011 #
#2860
b1000111100 #
#2865
b1000111101 #
#2870
b1000111110 #
#2875
b1000111111 #
#2880
b100 "
b1001000000 #
#2885
b1001000001 #
#2890
b1001000010 #
#2895
b1001000011 #
#2900
b1001000100 #
#2905
b1001000101 #
#2910
b1001000110 #
#2915
b1001000111 #
#2920
b1001001000 #
#2925
b1001001001 #
#2930
b1001001010 #
#2935
b1001001011 #
#2940
b1001001100 #
#2945
b1001001101 #
#2950
b1001001110 #
#2955
b1001001111 #
#2960
b101 "
b1001010000 #
#2965
b1001010001 #
#2970
b1001010010 #
#2975
b1001010011 #
#2980
b1001010100 #
#2985
b1001010101 #
#2990
b1001010110 #
#2995
b1001010111 #
#3000
b1001011000 #
#3005
b1001011001 #
#3010
b1001011010 #
#3015
b1001011011 #
#3020
b1001011100 #
#3025
b1001011101 #
#3030
b1001011110 #
#3035
b1001011111 #
#3040
b110 "
b1001100000 #
#3045
b1001100001 #
#3050
b1001100010 #
#3055
b1001100011 #
#3060
b1001100100 #
#3065
b1001100101 #
#3070
b1001100110 #
#3075
b1001100111 #
#3080
b1001101000 #
#3085
b1001101001 #
#3090
b1001101010 #
#3095
b1001101011 #
#3100
b1001101100 #
#3105
b1001101101 #
#3110
b1001101110 #
#3115
b1001101111 #
#3120
b111 "
b1001110000 #
#3125
b1001110001 #
#3130
b1001110010 #
#3135
b1001110011 #
#3140
b1001110100 #
#3145
b1001110101 #
#3150
b1001110110 #
#3155
b1001110111 #
#3160
b1001111000 #
#3165
b1001111001 #
#3170
b1001111010 #
#3175
b1001111011 #
#3180
b1001111100 #
#3185
b1001111101 #
#3190
b1001111110 #
#3195
b1001111111 #
#3200
b1000 "
b1010000000 #
#3205
b1010000001 #
#3210
b1010000010 #
#3215
b1010000011 #
#3220
b1010000100 #
#3225
b1010000101 #
#3230
b1010000110 #
#3235
b1010000111 #
#3240
b1010001000 #
#3245
b1010001001 #
#3250
b1010001010 #
#3255
b1010001011 #
#3260
b1010001100 #
#3265
b1010001101 #
#3270
b1010001110 #
#3275
b1010001111 #
#3280
b1001 "
b1010010000 #
#3285
b1010010001 #
#3290
b1010010010 #
#3295
b1010010011 #
#3300
b1010010100 #
#3305
b1010010101 #
#3310
b1010010110 #
#3315
b1010010111 #
#3320
b1010011000 #
#3325
b1010011001 #
#3330
b1010011010 #
#3335
b1010011011 #
#3340
b1010011100 #
#3345
b1010011101 #
#3350
b1010011110 #
#3355
b1010011111 #
#3360
b1010 "
b1010100000 #
#3365
b1010100001 #
#3370
b1010100010 #
#3375
b1010100011 #
#3380
b1010100100 #
#3385
b1010100101 #
#3390
b1010100110 #
#3395
b1010100111 #
#3400
b1010101000 #
#3405
b1010101001 #
#3410
b1010101010 #
#3415
b1010101011 #
#3420
b1010101100 #
#3425
b1010101101 #
#3430
b1010101110 #
#3435
b1010101111 #
#3440
b1011 "
b1010110000 #
#3445
b1010110001 #
#3450
b1010110010 #
#3455
b1010110011 #
#3460
b1010110100 #
#3465
b1010110101 #
#3470
b1010110110 #
#3475
b1010110111 #
#3480
b1010111000 #
#3485
b1010111001 #
#3490
b1010111010 #
#3495
b1010111011 #
#3500
b1010111100 #
#3505
b1010111101 #
#3510
b1010111110 #
#3515
b1010111111 #
#3520
b1100 "
b1011000000 #
#3525
b1011000001 #
#3530
b1011000010 #
#3535
b1011000011 #
#3540
b1011000100 #
#3545
b1011000101 #
#3550
b1011000110 #
#3555
b1011000111 #
#3560
b1011001000 #
#3565
b1011001001 #
#3570
b1011001010 #
#3575
b1011001011 #
#3580
b1011001100 #
#3585
b1011001101 #
#3590
b1011001110 #
#3595
b1011001111 #
#3600
b1101 "
b1011010000 #
#3605
b1011010001 #
#3610
b1011010010 #
#3615
b1011010011 #
#3620
b1011010100 #
#3625
b1011010101 #
#3630
b1011010110 #
#3635
b1011010111 #
#3640
b1011011000 #
#3645
b1011011001 #
#3650
b1011011010 #
#3655
b1011011011 #
#3660
b1011011100 #
#3665
b1011011101 #
#3670
b1011011110 #
#3675
b1011011111 #
#3680
b1110 "
b1011100000 #
#3685
b1011100001 #
#3690
b1011100010 #
#3695
b1011100011 #
#3700
b1011100100 #
#3705
b1011100101 #
#3710
b1011100110 #
#3715
b1011100111 #
#3720
b1011101000 #
#3725
b1011101001 #
#3730
b1011101010 #
#3735
b1011101011 #
#3740
b1011101100 #
#3745
b1011101101 #
#3750
b1011101110 #
#3755
b1011101111 #
#3760
b1111 "
b1011110000 #
#3765
b1011110001 #
#3770
b1011110010 #
#3775
b1011110011 #
#3780
b1011110100 #
#3785
b1011110101 #
#3790
b1011110110 #
#3795
b1011110111 #
#3800
b1011111000 #
#3805
b1011111001 #
#3810
b1011111010 #
#3815
b1011111011 #
#3820
b1011111100 #
#3825
b1011111101 #
#3830
b1011111110 #
#3835
b1011111111 #
#3840
b1111 "
b1100000000 #
#3845
b1100000001 #
#3850
b1100000010 #
#3855
b1100000011 #
#3860
b1100000100 #
#3865
b1100000101 #
#3870
b1100000110 #
#3875
b1100000111 #
#3880
b1100001000 #
#3885
b1100001001 #
#3890
b1100001010 #
#3895
b1100001011 #
#3900
b1100001100 #
#3905
b1100001101 #
#3910
b1100001110 #
#3915
b1100001111 #
#3920
b0 "
b1100010000 #
#3925
b1100010001 #
#3930
b1100010010 #
#3935
b1100010011 #
#3940
b1100010100 #
#3945
b1100010101 #
#3950
b1100010110 #
#3955
b1100010111 #
#3960
b1100011000 #
#3965
b1100011001 #
#3970
b1100011010 #
#3975
b1100011011 #
#3980
b1100011100 #
#3985
b1100011101 #
#3990
b1100011110 #
#3995
b1100011111 #
#4000
b1 "
b1100100000 #
#4005
b1100100001 #
#4010
b1100100010 #
#4015
b1100100011 #
#4020
b1100100100 #
#4025
b1100100101 #
#4030
b1100100110 #
#4035
b1100100111 #
#4040
b1100101000 #
#4045
b1100101001 #
#4050
b1100101010 #
#4055
b1100101011 #
#4060
b1100101100 #
#4065
b1100101101 #
#4070
b1100101110 #
#4075
b1100101111 #
#4080
b10 "
b1100110000 #
#4085
b1100110001 #
#4090
b1100110010 #
#4095
b1100110011 #
#4100
b1100110100 #
#4105
b1100110101 #
#4110
b1100110110 #
#4115
b1100110111 #
#4120
b1100111000 #
#4125
b1100111001 #
#4130
b1100111010 #
#4135
b1100111011 #
#4140
b1100111100 #
#4145
b1100111101 #
#4150
b1100111110 #
#4155
b1100111111 #
#4160
b11 "
b1101000000 #
#4165
b1101000001 #
#4170
b1101000010 #
#4175
b1101000011 #
#4180
b1101000100 #
#4185
b1101000101 #
#4190
b1101000110 #
#4195
b1101000111 #
#4200
b1101001000 #
#4205
b1101001001 #
#4210
b1101001010 #
#4215
b1101001011 #
#4220
b1101001100 #
#4225
b1101001101 #
#4230
b1101001110 #
#4235
b1101001111 #
#4240
b100 "
b1101010000 #
#4245
b1101010001 #
#4250
b1101010010 #
#4255
b1101010011 #
#4260
b1101010100 #
#4265
b1101010101 #
#4270
b1101010110 #
#4275
b1101010111 #
#4280
b1101011000 #
#4285
b1101011001 #
#4290
b1101011010 #
#4295
b1101011011 #
#4300
b1101011100 #
#4305
b1101011101 #
#4310
b1101011110 #
#4315
b1101011111 #
#4320
b101 "
b1101100000 #
#4325
b1101100001 #
#4330
b1101100010 #
#4335
b1101100011 #
#4340
b1101100100 #
#4345
b1101100101 #
#4350
b1101100110 #
#4355
b1101100111 #
#4360
b1101101000 #
#4365
b1101101001 #
#4370
b1101101010 #
#4375
b1101101011 #
#4380
b1101101100 #
#4385
b1101101101 #
#4390
b1101101110 #
#4395
b1101101111 #
#4400
b110 "
b1101110000 #
#4405
b1101110001 #
#4410
b1101110010 #
#4415
b1101110011 #
#4420
b1101110100 #
#4425
b1101110101 #
#4430
b1101110110 #
#4435
b1101110111 #
#4440
b1101111000 #
#4445
b1101111001 #
#4450
b1101111010 #
#4455
b1101111011 #
#4460
b1101111100 #
#4465
b1101111101 #
#4470
b1101111110 #
#4475
b1101111111 #
#4480
b111 "
b1110000000 #
#4485
b1110000001 #
#4490
b1110000010 #
#4495
b1110000011 #
#4500
b1110000100 #
#4505
b1110000101 #
#4510
b1110000110 #
#4515
b1110000111 #
#4520
b1110001000 #
#4525
b1110001001 #
#4530
b1110001010 #
#4535
b1110001011 #
#4540
b1110001100 #
#4545
b1110001101 #
#4550
b1110001110 #
#4555
b1110001111 #
#4560
b1000 "
b1110010000 #
#4565
b1110010001 #
#4570
b1110010010 #
#4575
b1110010011 #
#4580
b1110010100 #
#4585
b1110010101 #
#4590
b1110010110 #
#4595
b1110010111 #
#4600
b1110011000 #
#4605
b1110011001 #
#4610
b1110011010 #
#4615
b1110011011 #
#4620
b1110011100 #
#4625
b1110011101 #
#4630
b1110011110 #
#4635
b1110011111 #
#4640
b1001 "
b1110100000 #
#4645
b1110100001 #
#4650
b1110100010 #
#4655
b1110100011 #
#4660
b1110100100 #
#4665
b1110100101 #
#4670
b1110100110 #
#4675
b1110100111 #
#4680
b1110101000 #
#4685
b1110101001 #
#4690
b1110101010 #
#4695
b1110101011 #
#4700
b1110101100 #
#4705
b1110101101 #
#4710
b1110101110 #
#4715
b1110101111 #
#4720
b1010 "
b1110110000 #
#4725
b1110110001 #
#4730
b1110110010 #
#4735
b1110110011 #
#4740
b1110110100 #
#4745
b1110110101 #
#4750
b1110110110 #
#4755
b1110110111 #
#4760
b1110111000 #
#4765
b1110111001 #
#4770
b1110111010 #
#4775
b1110111011 #
#4780
b1110111100 #
#4785
b1110111101 #
#4790
b1110111110 #
#4795
b1110111111 #
#4800
b1011 "
b1111000000 #
#4805
b1111000001 #
#4810
b1111000010 #
#4815
b1111000011 #
#4820
b1111000100 #
#4825
b1111000101 #
