mux/mux 1/mux.v
//THIS IS A 2x1 MUX WITH OUT ENABLE INPUT
//CREATED BY SOUMIK GUHA ROY
module mux(I0,I1,I2,I3,s1,s0,y);
	input I0,I1,I2,I3,s1,s0;
	output y;
	reg y;
	always @( I0 or I1 or I2 or I3 or s1 or s0)	
	begin
		if (s1==0 && s0==0 )
			y<=I0;
		else if(s1==0 && s0==1)
			y<=I1;
		else if(s1==1 && s0==0)
			y<=I2;
		else
			y<=I3;
	end
endmodule

mux/mux 1/tb.v
//THIS IS THE TEST BENCH OF 2x1 MUX
//CREATED BY SOUMIK GUHA ROY
module tb;
	reg [5:0]	myData;
	mux myMux(myData[5],myData[4],myData[3],myData[2],myData[1],myData[0],out);
	initial begin
		$dumpfile ("wave.vcd");
		$dumpvars(0,tb);
		myData=6'b000000;
		#500 $finish;
	end

	always 
		#2 myData<=myData+1;
endmodule

mux/mux 1/wave.vcd
$date
	Fri Jul 13 21:00:45 2018
$end
$version
	Icarus Verilog
$end
$timescale
	1s
$end
$scope module tb $end
$var wire 1 ! out $end
$var reg 6 " myData [5:0] $end
$scope module myMux $end
$var wire 1 # I0 $end
$var wire 1 $ I1 $end
$var wire 1 % I2 $end
$var wire 1 & I3 $end
$var wire 1 ' s0 $end
$var wire 1 ( s1 $end
$var reg 1 ) y $end
$upscope $end
$upscope $end
$enddefinitions $end
#0
$dumpvars
0)
0(
0'
0&
0%
0$
0#
b0 "
0!
$end
#2
1'
b1 "
#4
1(
0'
b10 "
#6
1'
b11 "
#8
1&
0(
0'
b100 "
#10
1'
b101 "
#12
1(
0'
b110 "
#14
1)
1!
1'
b111 "
#16
0)
0!
1%
0&
0(
0'
b1000 "
#18
1'
b1001 "
#20
1)
1!
1(
0'
b1010 "
#22
0)
0!
1'
b1011 "
#24
1&
0(
0'
b1100 "
#26
1'
b1101 "
#28
1)
1!
1(
0'
b1110 "
#30
1'
b1111 "
#32
0)
0!
1$
0%
0&
0(
0'
b10000 "
#34
1)
1!
1'
b10001 "
#36
0)
0!
1(
0'
b10010 "
#38
1'
b10011 "
#40
1&
0(
0'
b10100 "
#42
1)
1!
1'
b10101 "
#44
0)
0!
1(
0'
b10110 "
#46
1)
1!
1'
b10111 "
#48
0)
0!
1%
0&
0(
0'
b11000 "
#50
1)
1!
1'
b11001 "
#52
1(
0'
b11010 "
#54
0)
0!
1'
b11011 "
#56
1&
0(
0'
b11100 "
#58
1)
1!
1'
b11101 "
#60
1(
0'
b11110 "
#62
1'
b11111 "
#64
1#
0$
0%
0&
0(
0'
b100000 "
#66
0)
0!
1'
b100001 "
#68
1(
0'
b100010 "
#70
1'
b100011 "
#72
1)
1!
1&
0(
0'
b100100 "
#74
0)
0!
1'
b100101 "
#76
1(
0'
b100110 "
#78
1)
1!
1'
b100111 "
#80
1%
0&
0(
0'
b101000 "
#82
0)
0!
1'
b101001 "
#84
1)
1!
1(
0'
b101010 "
#86
0)
0!
1'
b101011 "
#88
1)
1!
1&
0(
0'
b101100 "
#90
0)
0!
1'
b101101 "
#92
1)
1!
1(
0'
b101110 "
#94
1'
b101111 "
#96
1$
0%
0&
0(
0'
b110000 "
#98
1'
b110001 "
#100
0)
0!
1(
0'
b110010 "
#102
1'
b110011 "
#104
1)
1!
1&
0(
0'
b110100 "
#106
1'
b110101 "
#108
0)
0!
1(
0'
b110110 "
#110
1)
1!
1'
b110111 "
#112
1%
0&
0(
0'
b111000 "
#114
1'
b111001 "
#116
1(
0'
b111010 "
#118
0)
0!
1'
b111011 "
#120
1)
1!
1&
0(
0'
b111100 "
#122
1'
b111101 "
#124
1(
0'
b111110 "
#126
1'
b111111 "
#128
0)
0!
0#
0$
0%
0&
0(
0'
b0 "
#130
1'
b1 "
#132
1(
0'
b10 "
#134
1'
b11 "
#136
1&
0(
0'
b100 "
#138
1'
b101 "
#140
1(
0'
b110 "
#142
1)
1!
1'
b111 "
#144
0)
0!
1%
0&
0(
0'
b1000 "
#146
1'
b1001 "
#148
1)
1!
1(
0'
b1010 "
#150
0)
0!
1'
b1011 "
#152
1&
0(
0'
b1100 "
#154
1'
b1101 "
#156
1)
1!
1(
0'
b1110 "
#158
1'
b1111 "
#160
0)
0!
1$
0%
0&
0(
0'
b10000 "
#162
1)
1!
1'
b10001 "
#164
0)
0!
1(
0'
b10010 "
#166
1'
b10011 "
#168
1&
0(
0'
b10100 "
#170
1)
1!
1'
b10101 "
#172
0)
0!
1(
0'
b10110 "
#174
1)
1!
1'
b10111 "
#176
0)
0!
1%
0&
0(
0'
b11000 "
#178
1)
1!
1'
b11001 "
#180
1(
0'
b11010 "
#182
0)
0!
1'
b11011 "
#184
1&
0(
0'
b11100 "
#186
1)
1!
1'
b11101 "
#188
1(
0'
b11110 "
#190
1'
b11111 "
#192
1#
0$
0%
0&
0(
0'
b100000 "
#194
0)
0!
1'
b100001 "
#196
1(
0'
b100010 "
#198
1'
b100011 "
#200
1)
1!
1&
0(
0'
b100100 "
#202
0)
0!
1'
b100101 "
#204
1(
0'
b100110 "
#206
1)
1!
1'
b100111 "
#208
1%
0&
0(
0'
b101000 "
#210
0)
0!
1'
b101001 "
#212
1)
1!
1(
0'
b101010 "
#214
0)
0!
1'
b101011 "
#216
1)
1!
1&
0(
0'
b101100 "
#218
0)
0!
1'
b101101 "
#220
1)
1!
1(
0'
b101110 "
#222
1'
b101111 "
#224
1$
0%
0&
0(
0'
b110000 "
#226
1'
b110001 "
#228
0)
0!
1(
0'
b110010 "
#230
1'
b110011 "
#232
1)
1!
1&
0(
0'
b110100 "
#234
1'
b110101 "
#236
0)
0!
1(
0'
b110110 "
#238
1)
1!
1'
b110111 "
#240
1%
0&
0(
0'
b111000 "
#242
1'
b111001 "
#244
1(
0'
b111010 "
#246
0)
0!
1'
b111011 "
#248
1)
1!
1&
0(
0'
b111100 "
#250
1'
b111101 "
#252
1(
0'
b111110 "
#254
1'
b111111 "
#256
0)
0!
0#
0$
0%
0&
0(
0'
b0 "
#258
1'
b1 "
#260
1(
0'
b10 "
#262
1'
b11 "
#264
1&
0(
0'
b100 "
#266
1'
b101 "
#268
1(
0'
b110 "
#270
1)
1!
1'
b111 "
#272
0)
0!
1%
0&
0(
0'
b1000 "
#274
1'
b1001 "
#276
1)
1!
1(
0'
b1010 "
#278
0)
0!
1'
b1011 "
#280
1&
0(
0'
b1100 "
#282
1'
b1101 "
#284
1)
1!
1(
0'
b1110 "
#286
1'
b1111 "
#288
0)
0!
1$
0%
0&
0(
0'
b10000 "
#290
1)
1!
1'
b10001 "
#292
0)
0!
1(
0'
b10010 "
#294
1'
b10011 "
#296
1&
0(
0'
b10100 "
#298
1)
1!
1'
b10101 "
#300
0)
0!
1(
0'
b10110 "
#302
1)
1!
1'
b10111 "
#304
0)
0!
1%
0&
0(
0'
b11000 "
#306
1)
1!
1'
b11001 "
#308
1(
0'
b11010 "
#310
0)
0!
1'
b11011 "
#312
1&
0(
0'
b11100 "
#314
1)
1!
1'
b11101 "
#316
1(
0'
b11110 "
#318
1'
b11111 "
#320
1#
0$
0%
0&
0(
0'
b100000 "
#322
0)
0!
1'
b100001 "
#324
1(
0'
b100010 "
#326
1'
b100011 "
#328
1)
1!
1&
0(
0'
b100100 "
#330
0)
0!
1'
b100101 "
#332
1(
0'
b100110 "
#334
1)
1!
1'
b100111 "
#336
1%
0&
0(
0'
b101000 "
#338
0)
0!
1'
b101001 "
#340
1)
1!
1(
0'
b101010 "
#342
0)
0!
1'
b101011 "
#344
1)
1!
1&
0(
0'
b101100 "
#346
0)
0!
1'
b101101 "
#348
1)
1!
1(
0'
b101110 "
#350
1'
b101111 "
#352
1$
0%
0&
0(
0'
b110000 "
#354
1'
b110001 "
#356
0)
0!
1(
0'
b110010 "
#358
1'
b110011 "
#360
1)
1!
1&
0(
0'
b110100 "
#362
1'
b110101 "
#364
0)
0!
1(
0'
b110110 "
#366
1)
1!
1'
b110111 "
#368
1%
0&
0(
0'
b111000 "
#370
1'
b111001 "
#372
1(
0'
b111010 "
#374
0)
0!
1'
b111011 "
#376
1)
1!
1&
0(
0'
b111100 "
#378
1'
b111101 "
#380
1(
0'
b111110 "
#382
1'
b111111 "
#384
0)
0!
0#
0$
0%
0&
0(
0'
b0 "
#386
1'
b1 "
#388
1(
0'
b10 "
#390
1'
b11 "
#392
1&
0(
0'
b100 "
#394
1'
b101 "
#396
1(
0'
b110 "
#398
1)
1!
1'
b111 "
#400
0)
0!
1%
0&
0(
0'
b1000 "
#402
1'
b1001 "
#404
1)
1!
1(
0'
b1010 "
#406
0)
0!
1'
b1011 "
#408
1&
0(
0'
b1100 "
#410
1'
b1101 "
#412
1)
1!
1(
0'
b1110 "
#414
1'
b1111 "
#416
0)
0!
1$
0%
0&
0(
0'
b10000 "
#418
1)
1!
1'
b10001 "
#420
0)
0!
1(
0'
b10010 "
#422
1'
b10011 "
#424
1&
0(
0'
b10100 "
#426
1)
1!
1'
b10101 "
#428
0)
0!
1(
0'
b10110 "
#430
1)
1!
1'
b10111 "
#432
0)
0!
1%
0&
0(
0'
b11000 "
#434
1)
1!
1'
b11001 "
#436
1(
0'
b11010 "
#438
0)
0!
1'
b11011 "
#440
1&
0(
0'
b11100 "
#442
1)
1!
1'
b11101 "
#444
1(
0'
b11110 "
#446
1'
b11111 "
#448
1#
0$
0%
0&
0(
0'
b100000 "
#450
0)
0!
1'
b100001 "
#452
1(
0'
b100010 "
#454
1'
b100011 "
#456
1)
1!
1&
0(
0'
b100100 "
#458
0)
0!
1'
b100101 "
#460
1(
0'
b100110 "
#462
1)
1!
1'
b100111 "
#464
1%
0&
0(
0'
b101000 "
#466
0)
0!
1'
b101001 "
#468
1)
1!
1(
0'
b101010 "
#470
0)
0!
1'
b101011 "
#472
1)
1!
1&
0(
0'
b101100 "
#474
0)
0!
1'
b101101 "
#476
1)
1!
1(
0'
b101110 "
#478
1'
b101111 "
#480
1$
0%
0&
0(
0'
b110000 "
#482
1'
b110001 "
#484
0)
0!
1(
0'
b110010 "
#486
1'
b110011 "
#488
1)
1!
1&
0(
0'
b110100 "
#490
1'
b110101 "
#492
0)
0!
1(
0'
b110110 "
#494
1)
1!
1'
b110111 "
#496
1%
0&
0(
0'
b111000 "
#498
1'
b111001 "
#500
1(
0'
b111010 "
