Flipflops/SR/functional/2/SR_1.v
//Created by Soumik Guha Roy and moral support by the great Morris Mano
module ffSR(s,r,clock,reset,y);
// Using the RESET signal
	input s,r,clock,reset;
	output y;
	reg y;
	
	initial
		begin
			//This is the initial block
			//this block will be executed only 
			y=1'bx;
			$display("[SGR]Output initialized..");
		end
	always @(posedge reset)
			begin
				if (reset == 1'b1) //My assumption
				begin
					y=1'b0;
				end
			end
	always @( s && r )
	begin
		$display("Proh state");
		$monitor("Time: %0t, S: %b, R: %b, Y: %b", $time, s, r, y);
	end
	
	always @( s || r )
	begin
		$display("1-0");
		$monitor("Time: %0t, S: %b, R: %b, Y: %b", $time, s, r, y);
	end

	always @(posedge clock)
			begin
				$display("Hello... S:");	
				
				if (s == 1'b0 && r == 1'b0) 				//This always block will be executed when inputs are changed
				begin
					//y<=y;
				end
				else if (s == 1'b0 && r == 1'b1)
				begin
					y<=1'b0;
				end
				else if (s == 1'b1 && r == 1'b0)
				begin
					y<=1'b1;
				end
				else if (s == 1'b1 && r == 1'b1)
				begin
					y<=1'bx;
				end
			end
endmodule
//End of the definition of the SR function

Flipflops/SR/functional/2/tb.v
module tb;
	reg [3:0] myData;//S,R,CLOCK,Reset
	ffSR mySR(myData[3],myData[2],myData[1],myData[0],y_out); //module ffSR(s,r,clock,reset,y);
	initial 
		begin
			myData=4'b0000;
			$dumpfile("wave.vcd");
			$dumpvars(0,tb);
			#100 $finish;
				
		end

	always
		begin
			#5 myData<=myData+1;
			//#5 myData[1]<= !myData[1];
			//#5 myData[2]<= !myData[2];
			//#5 myData[3]<= !myData[3];
		end
endmodule

Flipflops/SR/functional/2/wave.vcd
$date
	Wed Aug 20 23:51:45 2025
$end
$version
	Icarus Verilog
$end
$timescale
	1s
$end
$scope module tb $end
$var wire 1 ! y_out $end
$var reg 4 " myData [3:0] $end
$scope module mySR $end
$var wire 1 # clock $end
$var wire 1 $ r $end
$var wire 1 % reset $end
$var wire 1 & s $end
$var reg 1 ! y $end
$upscope $end
$upscope $end
$enddefinitions $end
#0
$dumpvars
0&
0%
0$
0#
b0 "
x!
$end
#5
0!
1%
b1 "
#10
1#
0%
b10 "
#15
1%
b11 "
#20
1$
0#
0%
b100 "
#25
1%
b101 "
#30
1#
0%
b110 "
#35
1%
b111 "
#40
1&
0$
0#
0%
b1000 "
#45
1%
b1001 "
#50
1!
1#
0%
b1010 "
#55
0!
1%
b1011 "
#60
1$
0#
0%
b1100 "
#65
1%
b1101 "
#70
x!
1#
0%
b1110 "
#75
0!
1%
b1111 "
#80
0&
0$
0#
0%
b0 "
#85
1%
b1 "
#90
1#
0%
b10 "
#95
1%
b11 "
#100
1$
0#
0%
b100 "
