simple circuit/or gate/OR.v
module OR(a,b,c);
	input a,b;
	output c;
	reg c;
	always @ (a or b)	
	begin
		c<=a || b;
	end
endmodule

simple circuit/or gate/tb.v
module tb;
	reg[1:0] myData;
	OR ourOr(myData[1],myData[0],out);
	initial
	begin
		//intialize the mydata
		myData<=2'b00;
		$dumpfile("wave.vcd");
		$dumpvars(0,tb);
		#500 $finish;
	end
	always 
		begin
			#5 myData<=myData+1;
		end
endmodule

simple circuit/or gate/wave.vcd
$date
	Wed Aug 29 14:52:26 2018
$end
$version
	Icarus Verilog
$end
$timescale
	1s
$end
$scope module tb $end
$var wire 1 ! out $end
$var reg 2 " myData [1:0] $end
$scope module ourOr $end
$var wire 1 # a $end
$var wire 1 $ b $end
$var reg 1 % c $end
$upscope $end
$upscope $end
$enddefinitions $end
#0
$dumpvars
0%
0$
0#
b0 "
0!
$end
#5
1%
1!
1$
b1 "
#10
1#
0$
b10 "
#15
1$
b11 "
#20
0%
0!
0#
0$
b0 "
#25
1%
1!
1$
b1 "
#30
1#
0$
b10 "
#35
1$
b11 "
#40
0%
0!
0#
0$
b0 "
#45
1%
1!
1$
b1 "
#50
1#
0$
b10 "
#55
1$
b11 "
#60
0%
0!
0#
0$
b0 "
#65
1%
1!
1$
b1 "
#70
1#
0$
b10 "
#75
1$
b11 "
#80
0%
0!
0#
0$
b0 "
#85
1%
1!
1$
b1 "
#90
1#
0$
b10 "
#95
1$
b11 "
#100
0%
0!
0#
0$
b0 "
#105
1%
1!
1$
b1 "
#110
1#
0$
b10 "
#115
1$
b11 "
#120
0%
0!
0#
0$
b0 "
#125
1%
1!
1$
b1 "
#130
1#
0$
b10 "
#135
1$
b11 "
#140
0%
0!
0#
0$
b0 "
#145
1%
1!
1$
b1 "
#150
1#
0$
b10 "
#155
1$
b11 "
#160
0%
0!
0#
0$
b0 "
#165
1%
1!
1$
b1 "
#170
1#
0$
b10 "
#175
1$
b11 "
#180
0%
0!
0#
0$
b0 "
#185
1%
1!
1$
b1 "
#190
1#
0$
b10 "
#195
1$
b11 "
#200
0%
0!
0#
0$
b0 "
#205
1%
1!
1$
b1 "
#210
1#
0$
b10 "
#215
1$
b11 "
#220
0%
0!
0#
0$
b0 "
#225
1%
1!
1$
b1 "
#230
1#
0$
b10 "
#235
1$
b11 "
#240
0%
0!
0#
0$
b0 "
#245
1%
1!
1$
b1 "
#250
1#
0$
b10 "
#255
1$
b11 "
#260
0%
0!
0#
0$
b0 "
#265
1%
1!
1$
b1 "
#270
1#
0$
b10 "
#275
1$
b11 "
#280
0%
0!
0#
0$
b0 "
#285
1%
1!
1$
b1 "
#290
1#
0$
b10 "
#295
1$
b11 "
#300
0%
0!
0#
0$
b0 "
#305
1%
1!
1$
b1 "
#310
1#
0$
b10 "
#315
1$
b11 "
#320
0%
0!
0#
0$
b0 "
#325
1%
1!
1$
b1 "
#330
1#
0$
b10 "
#335
1$
b11 "
#340
0%
0!
0#
0$
b0 "
#345
1%
1!
1$
b1 "
#350
1#
0$
b10 "
#355
1$
b11 "
#360
0%
0!
0#
0$
b0 "
#365
1%
1!
1$
b1 "
#370
1#
0$
b10 "
#375
1$
b11 "
#380
0%
0!
0#
0$
b0 "
#385
1%
1!
1$
b1 "
#390
1#
0$
b10 "
#395
1$
b11 "
#400
0%
0!
0#
0$
b0 "
#405
1%
1!
1$
b1 "
#410
1#
0$
b10 "
#415
1$
b11 "
#420
0%
0!
0#
0$
b0 "
#425
1%
1!
1$
b1 "
#430
1#
0$
b10 "
#435
1$
b11 "
#440
0%
0!
0#
0$
b0 "
#445
1%
1!
1$
b1 "
#450
1#
0$
b10 "
#455
1$
b11 "
#460
0%
0!
0#
0$
b0 "
#465
1%
1!
1$
b1 "
#470
1#
0$
b10 "
#475
1$
b11 "
#480
0%
0!
0#
0$
b0 "
#485
1%
1!
1$
b1 "
#490
1#
0$
b10 "
#495
1$
b11 "
#500
0%
0!
0#
0$
b0 "
