Flipflops/JK/functional/1/JK.v
//Created by Soumik Guha Roy and moral support by the great Morris Mano and Jack Killbay
module ffJK(j,k,clock,y);
// Without using the RESET signal
	input j,k,clock;
	output y;
	reg y;
	
	initial
		begin
			//This is the initial block
			//this block will be executed only 
			y=1'b0;
		end

		always @(posedge clock)
			begin
				
				if (j == 1'b0 && k == 1'b0) 				//This always block will be executed when inputs are changed
				begin
					y=y;
				end
				else if (j == 1'b0 && k == 1'b1)
				begin
					y=j;
				end
				else if (j == 1'b1 && k == 1'b0)
				begin
					y=j;
				end
				else if (j == 1'b1 && k == 1'b1)
				begin
					y=!y; //Due to a new feedback in SR, resulting in JK
				end
			end
endmodule
//End of the behavioral/functional definition of the JK function

Flipflops/JK/functional/1/tb.v
module tb;
	reg [2:0] myData;//J,K,CLOCK
	ffJK myJK(myData[2],myData[1],myData[0],y_out); //module ffJK(j,k,clock,y);
	initial 
		begin
			myData=3'b011;
			$dumpfile("wave.vcd");
			$dumpvars(0,tb);
			#100 $finish;
				
		end

	always
		begin
			#5 myData<=myData+1;
		end
endmodule

Flipflops/JK/functional/1/wave.vcd
$date
	Thu Aug 21 00:37:11 2025
$end
$version
	Icarus Verilog
$end
$timescale
	1s
$end
$scope module tb $end
$var wire 1 ! y_out $end
$var reg 3 " myData [2:0] $end
$scope module myJK $end
$var wire 1 # clock $end
$var wire 1 $ j $end
$var wire 1 % k $end
$var reg 1 ! y $end
$upscope $end
$upscope $end
$enddefinitions $end
#0
$dumpvars
1%
0$
1#
b11 "
0!
$end
#5
1$
0%
0#
b100 "
#10
1!
1#
b101 "
#15
1%
0#
b110 "
#20
0!
1#
b111 "
#25
0$
0%
0#
b0 "
#30
1#
b1 "
#35
1%
0#
b10 "
#40
1#
b11 "
#45
1$
0%
0#
b100 "
#50
1!
1#
b101 "
#55
1%
0#
b110 "
#60
0!
1#
b111 "
#65
0$
0%
0#
b0 "
#70
1#
b1 "
#75
1%
0#
b10 "
#80
1#
b11 "
#85
1$
0%
0#
b100 "
#90
1!
1#
b101 "
#95
1%
0#
b110 "
#100
0!
1#
b111 "
