mux/mux 4/myMux.v
module myMux(I0,I1,I2,I3,S1,S0,E,Y);
	input I0,I1,I2,I3,S1,S0,E;
	output Y;
	reg Y;
	always @(S1 or S0 or E )
	begin
		if (E==1'b1)
		begin
			case ({S1,S0})
				2'b00: Y=I0;
				2'b01: Y=I1;
				2'b10: Y=I2;
				2'b11: Y=I3;
				default: Y=1'bx;
			endcase
		end
		else
			Y=1'bx;
	end
endmodule

mux/mux 4/tb.v
module tb;
	reg [6:0] myData;
	myMux m(myData[6],myData[5],myData[4],myData[3],myData[2],myData[1],myData[0],Y);
	initial begin
		myData=7'b0000000;
		$dumpfile("wave.vcd");
		$dumpvars(0,tb);
		#500 $finish;
	end

	always
		#5 myData<=myData+1;
endmodule

mux/mux 4/wave.vcd
$date
	Wed Jul 18 21:49:47 2018
$end
$version
	Icarus Verilog
$end
$timescale
	1s
$end
$scope module tb $end
$var wire 1 ! Y $end
$var reg 7 " myData [6:0] $end
$scope module m $end
$var wire 1 # E $end
$var wire 1 $ I0 $end
$var wire 1 % I1 $end
$var wire 1 & I2 $end
$var wire 1 ' I3 $end
$var wire 1 ( S0 $end
$var wire 1 ) S1 $end
$var reg 1 * Y $end
$upscope $end
$upscope $end
$enddefinitions $end
#0
$dumpvars
x*
0)
0(
0'
0&
0%
0$
0#
b0 "
x!
$end
#5
0*
0!
1#
b1 "
#10
x*
x!
1(
0#
b10 "
#15
0*
0!
1#
b11 "
#20
x*
x!
1)
0(
0#
b100 "
#25
0*
0!
1#
b101 "
#30
x*
x!
1(
0#
b110 "
#35
0*
0!
1#
b111 "
#40
x*
x!
1'
0)
0(
0#
b1000 "
#45
0*
0!
1#
b1001 "
#50
x*
x!
1(
0#
b1010 "
#55
0*
0!
1#
b1011 "
#60
x*
x!
1)
0(
0#
b1100 "
#65
0*
0!
1#
b1101 "
#70
x*
x!
1(
0#
b1110 "
#75
1*
1!
1#
b1111 "
#80
x*
x!
1&
0'
0)
0(
0#
b10000 "
#85
0*
0!
1#
b10001 "
#90
x*
x!
1(
0#
b10010 "
#95
0*
0!
1#
b10011 "
#100
x*
x!
1)
0(
0#
b10100 "
#105
1*
1!
1#
b10101 "
#110
x*
x!
1(
0#
b10110 "
#115
0*
0!
1#
b10111 "
#120
x*
x!
1'
0)
0(
0#
b11000 "
#125
0*
0!
1#
b11001 "
#130
x*
x!
1(
0#
b11010 "
#135
0*
0!
1#
b11011 "
#140
x*
x!
1)
0(
0#
b11100 "
#145
1*
1!
1#
b11101 "
#150
x*
x!
1(
0#
b11110 "
#155
1*
1!
1#
b11111 "
#160
x*
x!
1%
0&
0'
0)
0(
0#
b100000 "
#165
0*
0!
1#
b100001 "
#170
x*
x!
1(
0#
b100010 "
#175
1*
1!
1#
b100011 "
#180
x*
x!
1)
0(
0#
b100100 "
#185
0*
0!
1#
b100101 "
#190
x*
x!
1(
0#
b100110 "
#195
0*
0!
1#
b100111 "
#200
x*
x!
1'
0)
0(
0#
b101000 "
#205
0*
0!
1#
b101001 "
#210
x*
x!
1(
0#
b101010 "
#215
1*
1!
1#
b101011 "
#220
x*
x!
1)
0(
0#
b101100 "
#225
0*
0!
1#
b101101 "
#230
x*
x!
1(
0#
b101110 "
#235
1*
1!
1#
b101111 "
#240
x*
x!
1&
0'
0)
0(
0#
b110000 "
#245
0*
0!
1#
b110001 "
#250
x*
x!
1(
0#
b110010 "
#255
1*
1!
1#
b110011 "
#260
x*
x!
1)
0(
0#
b110100 "
#265
1*
1!
1#
b110101 "
#270
x*
x!
1(
0#
b110110 "
#275
0*
0!
1#
b110111 "
#280
x*
x!
1'
0)
0(
0#
b111000 "
#285
0*
0!
1#
b111001 "
#290
x*
x!
1(
0#
b111010 "
#295
1*
1!
1#
b111011 "
#300
x*
x!
1)
0(
0#
b111100 "
#305
1*
1!
1#
b111101 "
#310
x*
x!
1(
0#
b111110 "
#315
1*
1!
1#
b111111 "
#320
x*
x!
1$
0%
0&
0'
0)
0(
0#
b1000000 "
#325
1*
1!
1#
b1000001 "
#330
x*
x!
1(
0#
b1000010 "
#335
0*
0!
1#
b1000011 "
#340
x*
x!
1)
0(
0#
b1000100 "
#345
0*
0!
1#
b1000101 "
#350
x*
x!
1(
0#
b1000110 "
#355
0*
0!
1#
b1000111 "
#360
x*
x!
1'
0)
0(
0#
b1001000 "
#365
1*
1!
1#
b1001001 "
#370
x*
x!
1(
0#
b1001010 "
#375
0*
0!
1#
b1001011 "
#380
x*
x!
1)
0(
0#
b1001100 "
#385
0*
0!
1#
b1001101 "
#390
x*
x!
1(
0#
b1001110 "
#395
1*
1!
1#
b1001111 "
#400
x*
x!
1&
0'
0)
0(
0#
b1010000 "
#405
1*
1!
1#
b1010001 "
#410
x*
x!
1(
0#
b1010010 "
#415
0*
0!
1#
b1010011 "
#420
x*
x!
1)
0(
0#
b1010100 "
#425
1*
1!
1#
b1010101 "
#430
x*
x!
1(
0#
b1010110 "
#435
0*
0!
1#
b1010111 "
#440
x*
x!
1'
0)
0(
0#
b1011000 "
#445
1*
1!
1#
b1011001 "
#450
x*
x!
1(
0#
b1011010 "
#455
0*
0!
1#
b1011011 "
#460
x*
x!
1)
0(
0#
b1011100 "
#465
1*
1!
1#
b1011101 "
#470
x*
x!
1(
0#
b1011110 "
#475
1*
1!
1#
b1011111 "
#480
x*
x!
1%
0&
0'
0)
0(
0#
b1100000 "
#485
1*
1!
1#
b1100001 "
#490
x*
x!
1(
0#
b1100010 "
#495
1*
1!
1#
b1100011 "
#500
x*
x!
1)
0(
0#
b1100100 "
