Adder/Full_Adder/behavioral/myFA.v
//This module simulates Full adder operation using behavioral fashion
//Created by Soumik Guha Roy
module myFA(a,b,cin,cout,sum);
	input a,b,cin;
	output cout,sum;
	reg cout,sum;
	
	always @(a or b or cin )
	begin
		sum=(a^b^cin);
		cout=(a&b)|(cin&(a^b));
	end
endmodule

Adder/Full_Adder/behavioral/tb.v
//This is the test suite for the Full Adder
//Created by Soumik Guha Roy
module tb;
	reg[2:0] myData;
	myFA fa(myData[2],myData[1],myData[0],cout,sum);
	initial begin
		myData=3'b000;
		$dumpfile("wave.vcd");
		$dumpvars(0,tb);
		#500 $finish;
	end
	always
		begin
			#5 myData<=myData+1;
		end
endmodule

Adder/Full_Adder/behavioral/wave.vcd
$date
	Mon Jan 20 12:35:10 2020
$end
$version
	Icarus Verilog
$end
$timescale
	1s
$end
$scope module tb $end
$var wire 1 ! cout $end
$var wire 1 " sum $end
$var reg 3 # myData [2:0] $end
$scope module fa $end
$var wire 1 $ a $end
$var wire 1 % b $end
$var wire 1 & cin $end
$var reg 1 ' cout $end
$var reg 1 ( sum $end
$upscope $end
$upscope $end
$enddefinitions $end
#0
$dumpvars
0(
0'
0&
0%
0$
b0 #
0"
0!
$end
#5
1(
1"
1&
b1 #
#10
1%
0&
b10 #
#15
1'
1!
0(
0"
1&
b11 #
#20
0'
0!
1(
1"
1$
0%
0&
b100 #
#25
1'
1!
0(
0"
1&
b101 #
#30
1%
0&
b110 #
#35
1(
1"
1&
b111 #
#40
0'
0!
0(
0"
0$
0%
0&
b0 #
#45
1(
1"
1&
b1 #
#50
1%
0&
b10 #
#55
1'
1!
0(
0"
1&
b11 #
#60
0'
0!
1(
1"
1$
0%
0&
b100 #
#65
1'
1!
0(
0"
1&
b101 #
#70
1%
0&
b110 #
#75
1(
1"
1&
b111 #
#80
0'
0!
0(
0"
0$
0%
0&
b0 #
#85
1(
1"
1&
b1 #
#90
1%
0&
b10 #
#95
1'
1!
0(
0"
1&
b11 #
#100
0'
0!
1(
1"
1$
0%
0&
b100 #
#105
1'
1!
0(
0"
1&
b101 #
#110
1%
0&
b110 #
#115
1(
1"
1&
b111 #
#120
0'
0!
0(
0"
0$
0%
0&
b0 #
#125
1(
1"
1&
b1 #
#130
1%
0&
b10 #
#135
1'
1!
0(
0"
1&
b11 #
#140
0'
0!
1(
1"
1$
0%
0&
b100 #
#145
1'
1!
0(
0"
1&
b101 #
#150
1%
0&
b110 #
#155
1(
1"
1&
b111 #
#160
0'
0!
0(
0"
0$
0%
0&
b0 #
#165
1(
1"
1&
b1 #
#170
1%
0&
b10 #
#175
1'
1!
0(
0"
1&
b11 #
#180
0'
0!
1(
1"
1$
0%
0&
b100 #
#185
1'
1!
0(
0"
1&
b101 #
#190
1%
0&
b110 #
#195
1(
1"
1&
b111 #
#200
0'
0!
0(
0"
0$
0%
0&
b0 #
#205
1(
1"
1&
b1 #
#210
1%
0&
b10 #
#215
1'
1!
0(
0"
1&
b11 #
#220
0'
0!
1(
1"
1$
0%
0&
b100 #
#225
1'
1!
0(
0"
1&
b101 #
#230
1%
0&
b110 #
#235
1(
1"
1&
b111 #
#240
0'
0!
0(
0"
0$
0%
0&
b0 #
#245
1(
1"
1&
b1 #
#250
1%
0&
b10 #
#255
1'
1!
0(
0"
1&
b11 #
#260
0'
0!
1(
1"
1$
0%
0&
b100 #
#265
1'
1!
0(
0"
1&
b101 #
#270
1%
0&
b110 #
#275
1(
1"
1&
b111 #
#280
0'
0!
0(
0"
0$
0%
0&
b0 #
#285
1(
1"
1&
b1 #
#290
1%
0&
b10 #
#295
1'
1!
0(
0"
1&
b11 #
#300
0'
0!
1(
1"
1$
0%
0&
b100 #
#305
1'
1!
0(
0"
1&
b101 #
#310
1%
0&
b110 #
#315
1(
1"
1&
b111 #
#320
0'
0!
0(
0"
0$
0%
0&
b0 #
#325
1(
1"
1&
b1 #
#330
1%
0&
b10 #
#335
1'
1!
0(
0"
1&
b11 #
#340
0'
0!
1(
1"
1$
0%
0&
b100 #
#345
1'
1!
0(
0"
1&
b101 #
#350
1%
0&
b110 #
#355
1(
1"
1&
b111 #
#360
0'
0!
0(
0"
0$
0%
0&
b0 #
#365
1(
1"
1&
b1 #
#370
1%
0&
b10 #
#375
1'
1!
0(
0"
1&
b11 #
#380
0'
0!
1(
1"
1$
0%
0&
b100 #
#385
1'
1!
0(
0"
1&
b101 #
#390
1%
0&
b110 #
#395
1(
1"
1&
b111 #
#400
0'
0!
0(
0"
0$
0%
0&
b0 #
#405
1(
1"
1&
b1 #
#410
1%
0&
b10 #
#415
1'
1!
0(
0"
1&
b11 #
#420
0'
0!
1(
1"
1$
0%
0&
b100 #
#425
1'
1!
0(
0"
1&
b101 #
#430
1%
0&
b110 #
#435
1(
1"
1&
b111 #
#440
0'
0!
0(
0"
0$
0%
0&
b0 #
#445
1(
1"
1&
b1 #
#450
1%
0&
b10 #
#455
1'
1!
0(
0"
1&
b11 #
#460
0'
0!
1(
1"
1$
0%
0&
b100 #
#465
1'
1!
0(
0"
1&
b101 #
#470
1%
0&
b110 #
#475
1(
1"
1&
b111 #
#480
0'
0!
0(
0"
0$
0%
0&
b0 #
#485
1(
1"
1&
b1 #
#490
1%
0&
b10 #
#495
1'
1!
0(
0"
1&
b11 #
#500
0'
0!
1(
1"
1$
0%
0&
b100 #
