Adder/Parallel Adder/behavioral-Method 1/myFA.v
//This module simulates Full adder operation using behavioral fashion
//Created by Soumik Guha Royresponse.setHeader("Cache-Control", "private, no-store, no-cache, must-revalidate");
module myFA(a,b,cin,cout,sum);
	input a,b,cin;
	output cout,sum;
	reg cout,sum;
	
	always @(a or b or cin )
	begin
		sum=(a^b^cin);
		cout=(a&b)|(cin&(a^b));
	end
endmodule

Adder/Parallel Adder/behavioral-Method 1/tb.v
//This is the test suite for the Full Adder
//Created by Soumik Guha Roy
module tb;
	reg[3:0] operandA;
	reg[3:0] operandB;
	myFA fa0(operandA[0],operandB[0],1'b0,cout0,sum0);
	myFA fa1(operandA[1],operandB[1],cout0,cout1,sum1);
	myFA fa2(operandA[2],operandB[2],cout1,cout2,sum2);
	myFA fa3(operandA[3],operandB[3],cout2,cout3,sum3);
	initial begin
		operandA=4'b0000;
		operandB=4'b0000;
		$dumpfile("wave.vcd");
		$dumpvars(1,tb);
		#500 $finish;
	end
	always
		begin
			#5 operandA<=operandA+1;
			#5 operandB<=operandB+1;
		end
endmodule

Adder/Parallel Adder/behavioral-Method 1/wave.vcd
$date
	Sat Aug 11 11:44:51 2018
$end
$version
	Icarus Verilog
$end
$timescale
	1s
$end
$scope module tb $end
$var wire 1 ! cout0 $end
$var wire 1 " cout1 $end
$var wire 1 # cout2 $end
$var wire 1 $ cout3 $end
$var wire 1 % sum0 $end
$var wire 1 & sum1 $end
$var wire 1 ' sum2 $end
$var wire 1 ( sum3 $end
$var reg 4 ) operandA [3:0] $end
$var reg 4 * operandB [3:0] $end
$upscope $end
$enddefinitions $end
#0
$dumpvars
b0 *
b0 )
0(
0'
0&
0%
0$
0#
0"
0!
$end
#5
1%
b1 )
#10
1&
1!
0%
b1 *
#15
0'
0!
1%
0"
1&
b10 )
#20
1'
0%
1"
0&
b10 *
#25
1%
b11 )
#30
1&
1!
0%
b11 *
#35
0"
0(
0!
1%
1&
0#
1'
b100 )
#40
1(
0%
0&
1#
0'
b100 *
#45
1%
b101 )
#50
1&
1!
0%
b101 *
#55
0'
0!
1%
0"
1&
b110 )
#60
1'
0%
1"
0&
b110 *
#65
1%
b111 )
#70
1&
1!
0%
b111 *
#75
0#
0"
0!
1%
1&
1'
0$
1(
b1000 )
#80
0%
0&
0'
1$
0(
b1000 *
#85
1%
b1001 )
#90
1&
1!
0%
b1001 *
#95
0'
0!
1%
0"
1&
b1010 )
#100
1'
0%
1"
0&
b1010 *
#105
1%
b1011 )
#110
1&
1!
0%
b1011 *
#115
0"
0(
0!
1%
1&
0#
1'
b1100 )
#120
1(
0%
0&
1#
0'
b1100 *
#125
1%
b1101 )
#130
1&
1!
0%
b1101 *
#135
0'
0!
1%
0"
1&
b1110 )
#140
1'
0%
1"
0&
b1110 *
#145
1%
b1111 )
#150
1&
1!
0%
b1111 *
#155
0$
0#
0"
0!
1%
1&
1'
1(
b0 )
#160
0%
0&
0'
0(
b0 *
#165
1%
b1 )
#170
1&
1!
0%
b1 *
#175
0'
0!
1%
0"
1&
b10 )
#180
1'
0%
1"
0&
b10 *
#185
1%
b11 )
#190
1&
1!
0%
b11 *
#195
0"
0(
0!
1%
1&
0#
1'
b100 )
#200
1(
0%
0&
1#
0'
b100 *
#205
1%
b101 )
#210
1&
1!
0%
b101 *
#215
0'
0!
1%
0"
1&
b110 )
#220
1'
0%
1"
0&
b110 *
#225
1%
b111 )
#230
1&
1!
0%
b111 *
#235
0#
0"
0!
1%
1&
1'
0$
1(
b1000 )
#240
0%
0&
0'
1$
0(
b1000 *
#245
1%
b1001 )
#250
1&
1!
0%
b1001 *
#255
0'
0!
1%
0"
1&
b1010 )
#260
1'
0%
1"
0&
b1010 *
#265
1%
b1011 )
#270
1&
1!
0%
b1011 *
#275
0"
0(
0!
1%
1&
0#
1'
b1100 )
#280
1(
0%
0&
1#
0'
b1100 *
#285
1%
b1101 )
#290
1&
1!
0%
b1101 *
#295
0'
0!
1%
0"
1&
b1110 )
#300
1'
0%
1"
0&
b1110 *
#305
1%
b1111 )
#310
1&
1!
0%
b1111 *
#315
0$
0#
0"
0!
1%
1&
1'
1(
b0 )
#320
0%
0&
0'
0(
b0 *
#325
1%
b1 )
#330
1&
1!
0%
b1 *
#335
0'
0!
1%
0"
1&
b10 )
#340
1'
0%
1"
0&
b10 *
#345
1%
b11 )
#350
1&
1!
0%
b11 *
#355
0"
0(
0!
1%
1&
0#
1'
b100 )
#360
1(
0%
0&
1#
0'
b100 *
#365
1%
b101 )
#370
1&
1!
0%
b101 *
#375
0'
0!
1%
0"
1&
b110 )
#380
1'
0%
1"
0&
b110 *
#385
1%
b111 )
#390
1&
1!
0%
b111 *
#395
0#
0"
0!
1%
1&
1'
0$
1(
b1000 )
#400
0%
0&
0'
1$
0(
b1000 *
#405
1%
b1001 )
#410
1&
1!
0%
b1001 *
#415
0'
0!
1%
0"
1&
b1010 )
#420
1'
0%
1"
0&
b1010 *
#425
1%
b1011 )
#430
1&
1!
0%
b1011 *
#435
0"
0(
0!
1%
1&
0#
1'
b1100 )
#440
1(
0%
0&
1#
0'
b1100 *
#445
1%
b1101 )
#450
1&
1!
0%
b1101 *
#455
0'
0!
1%
0"
1&
b1110 )
#460
1'
0%
1"
0&
b1110 *
#465
1%
b1111 )
#470
1&
1!
0%
b1111 *
#475
0$
0#
0"
0!
1%
1&
1'
1(
b0 )
#480
0%
0&
0'
0(
b0 *
#485
1%
b1 )
#490
1&
1!
0%
b1 *
#495
0'
0!
1%
0"
1&
b10 )
#500
1'
0%
1"
0&
b10 *
