mux/mux 5/mux_4_1.v
module mux_4_1(s1,s0,i0,i1,i2,i3,e,y);
	input e,s1,s0,i0,i1,i2,i3;
	output y;
	reg y;
	
	always @ (e or s1 or s0)
	begin
		if (e==1'b0)
		begin
			y=1'bx;
		end
		else
		begin
			case ({s1,s0})
				2'b00:y=i0;
				2'b01:y=i1;
				2'b10:y=i2;
				2'b11:y=i3;
			endcase
		end
	end
endmodule

mux/mux 5/tb.v
module tb;
	reg [6:0] myData;
	mux_4_1 myMux(myData[6],myData[5],myData[4],myData[3],myData[2],myData[1],myData[0],y);
	
	initial 
		begin
			myData=7'b0;
			$dumpfile("wave.vcd");
			$dumpvars(0,tb);
			#500 $finish;
		end
	
	always
		begin
			#5 myData<=myData+1;
		end
endmodule

mux/mux 5/wave.vcd
$date
	Sat Sep  1 12:01:16 2018
$end
$version
	Icarus Verilog
$end
$timescale
	1s
$end
$scope module tb $end
$var wire 1 ! y $end
$var reg 7 " myData [6:0] $end
$scope module myMux $end
$var wire 1 # e $end
$var wire 1 $ i0 $end
$var wire 1 % i1 $end
$var wire 1 & i2 $end
$var wire 1 ' i3 $end
$var wire 1 ( s0 $end
$var wire 1 ) s1 $end
$var reg 1 * y $end
$upscope $end
$upscope $end
$enddefinitions $end
#0
$dumpvars
x*
0)
0(
0'
0&
0%
0$
0#
b0 "
x!
$end
#5
0*
0!
1#
b1 "
#10
x*
x!
1'
0#
b10 "
#15
0*
0!
1#
b11 "
#20
x*
x!
1&
0'
0#
b100 "
#25
0*
0!
1#
b101 "
#30
x*
x!
1'
0#
b110 "
#35
0*
0!
1#
b111 "
#40
x*
x!
1%
0&
0'
0#
b1000 "
#45
0*
0!
1#
b1001 "
#50
x*
x!
1'
0#
b1010 "
#55
0*
0!
1#
b1011 "
#60
x*
x!
1&
0'
0#
b1100 "
#65
0*
0!
1#
b1101 "
#70
x*
x!
1'
0#
b1110 "
#75
0*
0!
1#
b1111 "
#80
x*
x!
1$
0%
0&
0'
0#
b10000 "
#85
1*
1!
1#
b10001 "
#90
x*
x!
1'
0#
b10010 "
#95
1*
1!
1#
b10011 "
#100
x*
x!
1&
0'
0#
b10100 "
#105
1*
1!
1#
b10101 "
#110
x*
x!
1'
0#
b10110 "
#115
1*
1!
1#
b10111 "
#120
x*
x!
1%
0&
0'
0#
b11000 "
#125
1*
1!
1#
b11001 "
#130
x*
x!
1'
0#
b11010 "
#135
1*
1!
1#
b11011 "
#140
x*
x!
1&
0'
0#
b11100 "
#145
1*
1!
1#
b11101 "
#150
x*
x!
1'
0#
b11110 "
#155
1*
1!
1#
b11111 "
#160
x*
x!
1(
0$
0%
0&
0'
0#
b100000 "
#165
0*
0!
1#
b100001 "
#170
x*
x!
1'
0#
b100010 "
#175
0*
0!
1#
b100011 "
#180
x*
x!
1&
0'
0#
b100100 "
#185
0*
0!
1#
b100101 "
#190
x*
x!
1'
0#
b100110 "
#195
0*
0!
1#
b100111 "
#200
x*
x!
1%
0&
0'
0#
b101000 "
#205
1*
1!
1#
b101001 "
#210
x*
x!
1'
0#
b101010 "
#215
1*
1!
1#
b101011 "
#220
x*
x!
1&
0'
0#
b101100 "
#225
1*
1!
1#
b101101 "
#230
x*
x!
1'
0#
b101110 "
#235
1*
1!
1#
b101111 "
#240
x*
x!
1$
0%
0&
0'
0#
b110000 "
#245
0*
0!
1#
b110001 "
#250
x*
x!
1'
0#
b110010 "
#255
0*
0!
1#
b110011 "
#260
x*
x!
1&
0'
0#
b110100 "
#265
0*
0!
1#
b110101 "
#270
x*
x!
1'
0#
b110110 "
#275
0*
0!
1#
b110111 "
#280
x*
x!
1%
0&
0'
0#
b111000 "
#285
1*
1!
1#
b111001 "
#290
x*
x!
1'
0#
b111010 "
#295
1*
1!
1#
b111011 "
#300
x*
x!
1&
0'
0#
b111100 "
#305
1*
1!
1#
b111101 "
#310
x*
x!
1'
0#
b111110 "
#315
1*
1!
1#
b111111 "
#320
x*
x!
1)
0(
0$
0%
0&
0'
0#
b1000000 "
#325
0*
0!
1#
b1000001 "
#330
x*
x!
1'
0#
b1000010 "
#335
0*
0!
1#
b1000011 "
#340
x*
x!
1&
0'
0#
b1000100 "
#345
1*
1!
1#
b1000101 "
#350
x*
x!
1'
0#
b1000110 "
#355
1*
1!
1#
b1000111 "
#360
x*
x!
1%
0&
0'
0#
b1001000 "
#365
0*
0!
1#
b1001001 "
#370
x*
x!
1'
0#
b1001010 "
#375
0*
0!
1#
b1001011 "
#380
x*
x!
1&
0'
0#
b1001100 "
#385
1*
1!
1#
b1001101 "
#390
x*
x!
1'
0#
b1001110 "
#395
1*
1!
1#
b1001111 "
#400
x*
x!
1$
0%
0&
0'
0#
b1010000 "
#405
0*
0!
1#
b1010001 "
#410
x*
x!
1'
0#
b1010010 "
#415
0*
0!
1#
b1010011 "
#420
x*
x!
1&
0'
0#
b1010100 "
#425
1*
1!
1#
b1010101 "
#430
x*
x!
1'
0#
b1010110 "
#435
1*
1!
1#
b1010111 "
#440
x*
x!
1%
0&
0'
0#
b1011000 "
#445
0*
0!
1#
b1011001 "
#450
x*
x!
1'
0#
b1011010 "
#455
0*
0!
1#
b1011011 "
#460
x*
x!
1&
0'
0#
b1011100 "
#465
1*
1!
1#
b1011101 "
#470
x*
x!
1'
0#
b1011110 "
#475
1*
1!
1#
b1011111 "
#480
x*
x!
1(
0$
0%
0&
0'
0#
b1100000 "
#485
0*
0!
1#
b1100001 "
#490
x*
x!
1'
0#
b1100010 "
#495
1*
1!
1#
b1100011 "
#500
x*
x!
1&
0'
0#
b1100100 "
