counter/counter4/2/JK.v
//Created by Soumik Guha Roy and moral support by the great Morris Mano
module JK(j,k,clock,reset,y,y_bar);
// Using the RESET signal
	input j,k,clock,reset;
	output y,y_bar;
	reg y,y_bar;
	
	initial
		begin
			//This is the initial block
			//this block will be executed only 
			y=1'bx;
			y_bar=1'bx;
			$display("[JKFF]FF State  initialized..");
		end
	always @(posedge reset)
			begin
				if (reset == 1'b1) //My assumption
				begin
					y=1'b0;
					y_bar=1'b1;
				end
			end

	always @(posedge clock)
			begin
				$display("[JKFF]Pos clock J=%b K=%b|Q=%b Q'=%b",j,k,y,y_bar);	
				
				if (j == 1'b0 && k == 1'b0) 				//This always block will be executed when inputs are changed
				begin
					//y<=y;
					$display("No Change Zone..");
				end
				else if (j == 1'b0 && k == 1'b1)
				begin
					$display("At Set Zone..");
					y<=1'b0;
					y_bar<=1'b1;
				end
				else if (j == 1'b1 && k == 1'b0)
				begin
					$display("At Reset Zone..");
					y<=1'b1;
					y_bar<=1'b0;
				end
				else if (j == 1'b1 && k == 1'b1)
				begin
					$display("At Toggle Zone..");
					y=!y;
					y_bar=!y;
				end
			end
endmodule
//End of the functional/behavioral definition of the JK function

counter/counter4/2/counter_4bit.v
//Created by Soumik Guha Roy and moral support by the great Morris Mano
//4 bit asynchronous MOD 5 counter 
module ccCounter(clock_counter,reset_counter,y);
	input clock_counter,reset_counter;
	output[3:0]  y;
	wire[3:0] y;
	wire[3:0] y_bar;

	JK jk_0(1'b1,1'b1,clock_counter,reset_counter,y[0],y_bar[0]); //module JK(j,k,clock,reset,y,y_bar); //LSB 
	JK jk_1(1'b1,1'b1,y_bar[0],reset_counter,y[1],y_bar[1]); //module JK(j,k,clock,reset,y,y_bar); 
	JK jk_2(1'b1,1'b1,y_bar[1],reset_counter,y[2],y_bar[2]); //module JK(j,k,clock,reset,y,y_bar); 
	JK jk_3(1'b1,1'b1,y_bar[2],reset_counter,y[3],y_bar[3]); //module JK(j,k,clock,reset,y,y_bar); //MSB
endmodule
//End of the functional/behavioral definition of the JK function

counter/counter4/2/tb_counter_4bit.v
module tb;
	reg clock;
	reg reset;
	wire [3:0] myOutput;

	ccCounter myCounter(clock,reset,myOutput);//module ccCounter(clock,reset);
	initial 
		begin
			clock=1'b0;
			reset=1'b1; //Be carefull about it ...without reset the counter output will be donot care
			$dumpfile("wave.vcd");
			$dumpvars(0,tb);
			#400 $finish;
				
		end

	always
		begin
			#5 clock=~clock;
			$display("New Clock");	
		end
endmodule

counter/counter4/2/wave.vcd
$date
	Tue Aug 26 10:36:29 2025
$end
$version
	Icarus Verilog
$end
$timescale
	1s
$end
$scope module tb $end
$var wire 4 ! myOutput [3:0] $end
$var reg 1 " clock $end
$var reg 1 # reset $end
$scope module myCounter $end
$var wire 1 " clock_counter $end
$var wire 1 # reset_counter $end
$var wire 4 $ y_bar [3:0] $end
$var wire 4 % y [3:0] $end
$scope module jk_0 $end
$var wire 1 " clock $end
$var wire 1 & j $end
$var wire 1 ' k $end
$var wire 1 # reset $end
$var reg 1 ( y $end
$var reg 1 ) y_bar $end
$upscope $end
$scope module jk_1 $end
$var wire 1 * clock $end
$var wire 1 + j $end
$var wire 1 , k $end
$var wire 1 # reset $end
$var reg 1 - y $end
$var reg 1 . y_bar $end
$upscope $end
$scope module jk_2 $end
$var wire 1 / clock $end
$var wire 1 0 j $end
$var wire 1 1 k $end
$var wire 1 # reset $end
$var reg 1 2 y $end
$var reg 1 3 y_bar $end
$upscope $end
$scope module jk_3 $end
$var wire 1 4 clock $end
$var wire 1 5 j $end
$var wire 1 6 k $end
$var wire 1 # reset $end
$var reg 1 7 y $end
$var reg 1 8 y_bar $end
$upscope $end
$upscope $end
$upscope $end
$enddefinitions $end
#0
$dumpvars
08
17
16
15
04
03
12
11
10
0/
0.
1-
1,
1+
1*
1)
0(
1'
1&
b1110 %
b1 $
1#
0"
b1110 !
$end
#5
0*
b0 $
0)
b1111 !
b1111 %
1(
1"
#10
0"
#15
18
07
14
13
02
1/
1.
0-
1*
b1111 $
1)
b0 !
b0 %
0(
1"
#20
0"
#25
0*
b1110 $
0)
b1 !
b1 %
1(
1"
#30
0"
#35
0/
0.
1-
1*
b1101 $
1)
b10 !
b10 %
0(
1"
#40
0"
#45
0*
b1100 $
0)
b11 !
b11 %
1(
1"
#50
0"
#55
04
03
12
1/
1.
0-
1*
b1011 $
1)
b100 !
b100 %
0(
1"
#60
0"
#65
0*
b1010 $
0)
b101 !
b101 %
1(
1"
#70
0"
#75
0/
0.
1-
1*
b1001 $
1)
b110 !
b110 %
0(
1"
#80
0"
#85
0*
b1000 $
0)
b111 !
b111 %
1(
1"
#90
0"
#95
08
17
14
13
02
1/
1.
0-
1*
b111 $
1)
b1000 !
b1000 %
0(
1"
#100
0"
#105
0*
b110 $
0)
b1001 !
b1001 %
1(
1"
#110
0"
#115
0/
0.
1-
1*
b101 $
1)
b1010 !
b1010 %
0(
1"
#120
0"
#125
0*
b100 $
0)
b1011 !
b1011 %
1(
1"
#130
0"
#135
04
03
12
1/
1.
0-
1*
b11 $
1)
b1100 !
b1100 %
0(
1"
#140
0"
#145
0*
b10 $
0)
b1101 !
b1101 %
1(
1"
#150
0"
#155
0/
0.
1-
1*
b1 $
1)
b1110 !
b1110 %
0(
1"
#160
0"
#165
0*
b0 $
0)
b1111 !
b1111 %
1(
1"
#170
0"
#175
18
07
14
13
02
1/
1.
0-
1*
b1111 $
1)
b0 !
b0 %
0(
1"
#180
0"
#185
0*
b1110 $
0)
b1 !
b1 %
1(
1"
#190
0"
#195
0/
0.
1-
1*
b1101 $
1)
b10 !
b10 %
0(
1"
#200
0"
#205
0*
b1100 $
0)
b11 !
b11 %
1(
1"
#210
0"
#215
04
03
12
1/
1.
0-
1*
b1011 $
1)
b100 !
b100 %
0(
1"
#220
0"
#225
0*
b1010 $
0)
b101 !
b101 %
1(
1"
#230
0"
#235
0/
0.
1-
1*
b1001 $
1)
b110 !
b110 %
0(
1"
#240
0"
#245
0*
b1000 $
0)
b111 !
b111 %
1(
1"
#250
0"
#255
08
17
14
13
02
1/
1.
0-
1*
b111 $
1)
b1000 !
b1000 %
0(
1"
#260
0"
#265
0*
b110 $
0)
b1001 !
b1001 %
1(
1"
#270
0"
#275
0/
0.
1-
1*
b101 $
1)
b1010 !
b1010 %
0(
1"
#280
0"
#285
0*
b100 $
0)
b1011 !
b1011 %
1(
1"
#290
0"
#295
04
03
12
1/
1.
0-
1*
b11 $
1)
b1100 !
b1100 %
0(
1"
#300
0"
#305
0*
b10 $
0)
b1101 !
b1101 %
1(
1"
#310
0"
#315
0/
0.
1-
1*
b1 $
1)
b1110 !
b1110 %
0(
1"
#320
0"
#325
0*
b0 $
0)
b1111 !
b1111 %
1(
1"
#330
0"
#335
18
07
14
13
02
1/
1.
0-
1*
b1111 $
1)
b0 !
b0 %
0(
1"
#340
0"
#345
0*
b1110 $
0)
b1 !
b1 %
1(
1"
#350
0"
#355
0/
0.
1-
1*
b1101 $
1)
b10 !
b10 %
0(
1"
#360
0"
#365
0*
b1100 $
0)
b11 !
b11 %
1(
1"
#370
0"
#375
04
03
12
1/
1.
0-
1*
b1011 $
1)
b100 !
b100 %
0(
1"
#380
0"
#385
0*
b1010 $
0)
b101 !
b101 %
1(
1"
#390
0"
#395
0/
0.
1-
1*
b1001 $
1)
b110 !
b110 %
0(
1"
