decoder/2_4_Decoder/decoder_2_4.v
module decoder_2_4(i1,i0,e,y0,y1,y2,y3);
	input i1,i0,e;
	output y0,y1,y2,y3;
	reg y0,y1,y2,y3;
	
	always @ (i1 or i0 or e)
		begin
			y0=1'b0;y1=1'b0;y2=1'b0;y3=1'b0;
			
			if (e==1'b1)
			begin
				case ({i1,i0})
					2'b00:y0=1'b1;
					2'b01:y1=1'b1;
					2'b10:y2=1'b1;
					2'b11:y3=1'b1;
				endcase
			end
		end
endmodule

decoder/2_4_Decoder/tb.v
module tb;
	reg[2:0] myData;
	decoder_2_4 dcode_2_4(myData[2],myData[1],myData[0],o0,o1,o2,o3);
	initial
		begin
			myData=3'b000;
			$dumpfile("decoder_2_4_wave.vcd");
			$dumpvars(0,tb);
			#500 $finish;
		end
	always
		begin
			#5 myData=myData+1;
		end
	
endmodule

decoder/2_4_Decoder/decoder_2_4_wave.vcd
$date
	Wed Sep 19 10:25:10 2018
$end
$version
	Icarus Verilog
$end
$timescale
	1s
$end
$scope module tb $end
$var wire 1 ! o0 $end
$var wire 1 " o1 $end
$var wire 1 # o2 $end
$var wire 1 $ o3 $end
$var reg 3 % myData [2:0] $end
$scope module dcode_2_4 $end
$var wire 1 & e $end
$var wire 1 ' i0 $end
$var wire 1 ( i1 $end
$var reg 1 ) y0 $end
$var reg 1 * y1 $end
$var reg 1 + y2 $end
$var reg 1 , y3 $end
$upscope $end
$upscope $end
$enddefinitions $end
#0
$dumpvars
0,
0+
0*
0)
0(
0'
0&
b0 %
0$
0#
0"
0!
$end
#5
1)
1!
1&
b1 %
#10
0)
0!
1'
0&
b10 %
#15
1*
1"
1&
b11 %
#20
0*
0"
1(
0'
0&
b100 %
#25
1+
1#
1&
b101 %
#30
0+
0#
1'
0&
b110 %
#35
1,
1$
1&
b111 %
#40
0,
0$
0(
0'
0&
b0 %
#45
1)
1!
1&
b1 %
#50
0)
0!
1'
0&
b10 %
#55
1*
1"
1&
b11 %
#60
0*
0"
1(
0'
0&
b100 %
#65
1+
1#
1&
b101 %
#70
0+
0#
1'
0&
b110 %
#75
1,
1$
1&
b111 %
#80
0,
0$
0(
0'
0&
b0 %
#85
1)
1!
1&
b1 %
#90
0)
0!
1'
0&
b10 %
#95
1*
1"
1&
b11 %
#100
0*
0"
1(
0'
0&
b100 %
#105
1+
1#
1&
b101 %
#110
0+
0#
1'
0&
b110 %
#115
1,
1$
1&
b111 %
#120
0,
0$
0(
0'
0&
b0 %
#125
1)
1!
1&
b1 %
#130
0)
0!
1'
0&
b10 %
#135
1*
1"
1&
b11 %
#140
0*
0"
1(
0'
0&
b100 %
#145
1+
1#
1&
b101 %
#150
0+
0#
1'
0&
b110 %
#155
1,
1$
1&
b111 %
#160
0,
0$
0(
0'
0&
b0 %
#165
1)
1!
1&
b1 %
#170
0)
0!
1'
0&
b10 %
#175
1*
1"
1&
b11 %
#180
0*
0"
1(
0'
0&
b100 %
#185
1+
1#
1&
b101 %
#190
0+
0#
1'
0&
b110 %
#195
1,
1$
1&
b111 %
#200
0,
0$
0(
0'
0&
b0 %
#205
1)
1!
1&
b1 %
#210
0)
0!
1'
0&
b10 %
#215
1*
1"
1&
b11 %
#220
0*
0"
1(
0'
0&
b100 %
#225
1+
1#
1&
b101 %
#230
0+
0#
1'
0&
b110 %
#235
1,
1$
1&
b111 %
#240
0,
0$
0(
0'
0&
b0 %
#245
1)
1!
1&
b1 %
#250
0)
0!
1'
0&
b10 %
#255
1*
1"
1&
b11 %
#260
0*
0"
1(
0'
0&
b100 %
#265
1+
1#
1&
b101 %
#270
0+
0#
1'
0&
b110 %
#275
1,
1$
1&
b111 %
#280
0,
0$
0(
0'
0&
b0 %
#285
1)
1!
1&
b1 %
#290
0)
0!
1'
0&
b10 %
#295
1*
1"
1&
b11 %
#300
0*
0"
1(
0'
0&
b100 %
#305
1+
1#
1&
b101 %
#310
0+
0#
1'
0&
b110 %
#315
1,
1$
1&
b111 %
#320
0,
0$
0(
0'
0&
b0 %
#325
1)
1!
1&
b1 %
#330
0)
0!
1'
0&
b10 %
#335
1*
1"
1&
b11 %
#340
0*
0"
1(
0'
0&
b100 %
#345
1+
1#
1&
b101 %
#350
0+
0#
1'
0&
b110 %
#355
1,
1$
1&
b111 %
#360
0,
0$
0(
0'
0&
b0 %
#365
1)
1!
1&
b1 %
#370
0)
0!
1'
0&
b10 %
#375
1*
1"
1&
b11 %
#380
0*
0"
1(
0'
0&
b100 %
#385
1+
1#
1&
b101 %
#390
0+
0#
1'
0&
b110 %
#395
1,
1$
1&
b111 %
#400
0,
0$
0(
0'
0&
b0 %
#405
1)
1!
1&
b1 %
#410
0)
0!
1'
0&
b10 %
#415
1*
1"
1&
b11 %
#420
0*
0"
1(
0'
0&
b100 %
#425
1+
1#
1&
b101 %
#430
0+
0#
1'
0&
b110 %
#435
1,
1$
1&
b111 %
#440
0,
0$
0(
0'
0&
b0 %
#445
1)
1!
1&
b1 %
#450
0)
0!
1'
0&
b10 %
#455
1*
1"
1&
b11 %
#460
0*
0"
1(
0'
0&
b100 %
#465
1+
1#
1&
b101 %
#470
0+
0#
1'
0&
b110 %
#475
1,
1$
1&
b111 %
#480
0,
0$
0(
0'
0&
b0 %
#485
1)
1!
1&
b1 %
#490
0)
0!
1'
0&
b10 %
#495
1*
1"
1&
b11 %
#500
0*
0"
1(
0'
0&
b100 %
